{"data":[{"keyword":"administrador de contas","numberOfApps":275,"searchVolume":14.0,"chance":55,"rank":6},{"keyword":"agenda de contas a pagar","numberOfApps":27,"searchVolume":22.0,"chance":52,"rank":5},{"keyword":"aplicativo finanças","numberOfApps":4502,"searchVolume":23.0,"chance":37,"rank":20},{"keyword":"aplicativos","numberOfApps":226872,"searchVolume":54.0,"chance":10,"rank":222},{"keyword":"app","numberOfApps":63392,"searchVolume":52.0,"chance":0,"rank":84},{"keyword":"app app","numberOfApps":63401,"searchVolume":31.0,"chance":4,"rank":88},{"keyword":"app apps","numberOfApps":63401,"searchVolume":31.0,"chance":4,"rank":88},{"keyword":"app de","numberOfApps":112674,"searchVolume":31.0,"chance":8,"rank":76},{"keyword":"app de finanças","numberOfApps":90768,"searchVolume":25.0,"chance":34,"rank":11},{"keyword":"app dinheiro","numberOfApps":1452,"searchVolume":24.0,"chance":39,"rank":4},{"keyword":"app finanças","numberOfApps":90768,"searchVolume":27.0,"chance":34,"rank":12},{"keyword":"app for","numberOfApps":63545,"searchVolume":19.0,"chance":4,"rank":88},{"keyword":"app gratis","numberOfApps":232138,"searchVolume":31.0,"chance":4,"rank":224},{"keyword":"app in","numberOfApps":63545,"searchVolume":21.0,"chance":4,"rank":88},{"keyword":"app pagamento","numberOfApps":549,"searchVolume":34.0,"chance":38,"rank":1},{"keyword":"apps","numberOfApps":63391,"searchVolume":52.0,"chance":0,"rank":84},{"keyword":"apps app","numberOfApps":63401,"searchVolume":31.0,"chance":4,"rank":88},{"keyword":"apps apps","numberOfApps":63401,"searchVolume":31.0,"chance":4,"rank":88},{"keyword":"apps dinheiro","numberOfApps":1452,"searchVolume":24.0,"chance":38,"rank":2},{"keyword":"ar","numberOfApps":38496,"searchVolume":52.0,"chance":37,"rank":28},{"keyword":"bilhete","numberOfApps":142,"searchVolume":46.0,"chance":47,"rank":4},{"keyword":"bilhete unico","numberOfApps":336,"searchVolume":52.0,"chance":47,"rank":5},{"keyword":"bilhete único","numberOfApps":142,"searchVolume":52.0,"chance":47,"rank":4},{"keyword":"boleto de pagamento","numberOfApps":27,"searchVolume":32.0,"chance":54,"rank":1},{"keyword":"celular","numberOfApps":784,"searchVolume":69.0,"chance":50,"rank":11},{"keyword":"celular roubado","numberOfApps":784,"searchVolume":32.0,"chance":36,"rank":9},{"keyword":"celulares","numberOfApps":846,"searchVolume":69.0,"chance":34,"rank":3},{"keyword":"claro recarga","numberOfApps":680,"searchVolume":44.0,"chance":46,"rank":11},{"keyword":"como ganhar dinheiro","numberOfApps":1448,"searchVolume":51.0,"chance":52,"rank":10},{"keyword":"compras mercado","numberOfApps":1079,"searchVolume":32.0,"chance":29,"rank":6},{"keyword":"consulta de saldo","numberOfApps":1131,"searchVolume":34.0,"chance":39,"rank":10},{"keyword":"conta","numberOfApps":1487,"searchVolume":49.0,"chance":28,"rank":15},{"keyword":"contabilidade","numberOfApps":409,"searchVolume":51.0,"chance":49,"rank":6},{"keyword":"contas","numberOfApps":275,"searchVolume":49.0,"chance":53,"rank":8},{"keyword":"contas a pagar","numberOfApps":275,"searchVolume":42.0,"chance":53,"rank":5},{"keyword":"contas a pagar e receber","numberOfApps":27,"searchVolume":31.0,"chance":51,"rank":6},{"keyword":"contas a receber","numberOfApps":275,"searchVolume":32.0,"chance":56,"rank":6},{"keyword":"controlar dinheiro","numberOfApps":1448,"searchVolume":21.0,"chance":47,"rank":8},{"keyword":"controle contas","numberOfApps":292,"searchVolume":23.0,"chance":51,"rank":6},{"keyword":"controle contas a pagar","numberOfApps":27,"searchVolume":27.0,"chance":50,"rank":6},{"keyword":"controle de contas a pagar","numberOfApps":27,"searchVolume":31.0,"chance":51,"rank":6},{"keyword":"cool","numberOfApps":63380,"searchVolume":52.0,"chance":31,"rank":133},{"keyword":"código qr","numberOfApps":5710,"searchVolume":42.0,"chance":52,"rank":22},{"keyword":"dinheirama","numberOfApps":1457,"searchVolume":33.0,"chance":45,"rank":21},{"keyword":"dinheiro","numberOfApps":1452,"searchVolume":52.0,"chance":47,"rank":11},{"keyword":"dinheiro app","numberOfApps":1452,"searchVolume":17.0,"chance":39,"rank":3},{"keyword":"dinheiro brasileiro","numberOfApps":1448,"searchVolume":33.0,"chance":49,"rank":5},{"keyword":"dinheiro gratis","numberOfApps":658,"searchVolume":31.0,"chance":46,"rank":7},{"keyword":"dinheiro pagamento","numberOfApps":47,"searchVolume":19.0,"chance":40,"rank":2},{"keyword":"download app","numberOfApps":63545,"searchVolume":41.0,"chance":4,"rank":88},{"keyword":"economizar dinheiro","numberOfApps":1448,"searchVolume":34.0,"chance":47,"rank":9},{"keyword":"enviar","numberOfApps":337,"searchVolume":47.0,"chance":45,"rank":7},{"keyword":"enviar app","numberOfApps":337,"searchVolume":32.0,"chance":39,"rank":2},{"keyword":"financa","numberOfApps":90742,"searchVolume":23.0,"chance":35,"rank":22},{"keyword":"financas pessoais","numberOfApps":4500,"searchVolume":41.0,"chance":50,"rank":48},{"keyword":"finance","numberOfApps":90645,"searchVolume":41.0,"chance":39,"rank":21},{"keyword":"financeira","numberOfApps":4580,"searchVolume":44.0,"chance":37,"rank":24},{"keyword":"financeiro","numberOfApps":4544,"searchVolume":44.0,"chance":33,"rank":22},{"keyword":"finances","numberOfApps":90665,"searchVolume":41.0,"chance":31,"rank":20},{"keyword":"financial","numberOfApps":92559,"searchVolume":41.0,"chance":29,"rank":26},{"keyword":"finança","numberOfApps":90774,"searchVolume":43.0,"chance":35,"rank":22},{"keyword":"finanças","numberOfApps":90763,"searchVolume":43.0,"chance":44,"rank":24},{"keyword":"finanças empresa","numberOfApps":5303,"searchVolume":21.0,"chance":36,"rank":23},{"keyword":"finanças empresariais","numberOfApps":4500,"searchVolume":28.0,"chance":28,"rank":21},{"keyword":"finanças empresarial","numberOfApps":4513,"searchVolume":17.0,"chance":34,"rank":22},{"keyword":"finanças pessoais","numberOfApps":4500,"searchVolume":41.0,"chance":34,"rank":21},{"keyword":"free apps","numberOfApps":45603,"searchVolume":34.0,"chance":3,"rank":84},{"keyword":"ganhar dinheiro","numberOfApps":1484,"searchVolume":49.0,"chance":44,"rank":12},{"keyword":"ganhe dinheiro","numberOfApps":1448,"searchVolume":49.0,"chance":43,"rank":8},{"keyword":"gerenciador de contas","numberOfApps":287,"searchVolume":31.0,"chance":52,"rank":7},{"keyword":"gerenciamento de contas","numberOfApps":275,"searchVolume":22.0,"chance":54,"rank":6},{"keyword":"gerenciar contas","numberOfApps":275,"searchVolume":27.0,"chance":54,"rank":7},{"keyword":"gratis","numberOfApps":226499,"searchVolume":42.0,"chance":7,"rank":227},{"keyword":"gratis app","numberOfApps":226452,"searchVolume":14.0,"chance":10,"rank":77},{"keyword":"gratis gratis","numberOfApps":226496,"searchVolume":21.0,"chance":9,"rank":230},{"keyword":"gratis por","numberOfApps":226496,"searchVolume":12.0,"chance":5,"rank":221},{"keyword":"gratuitas","numberOfApps":226531,"searchVolume":43.0,"chance":9,"rank":223},{"keyword":"gratuito","numberOfApps":243895,"searchVolume":43.0,"chance":6,"rank":235},{"keyword":"gratuitos","numberOfApps":226604,"searchVolume":43.0,"chance":5,"rank":227},{"keyword":"grátis","numberOfApps":226499,"searchVolume":44.0,"chance":8,"rank":229},{"keyword":"grátis grátis","numberOfApps":226441,"searchVolume":22.0,"chance":9,"rank":230},{"keyword":"guardar dinheiro","numberOfApps":1448,"searchVolume":32.0,"chance":45,"rank":8},{"keyword":"ipad app","numberOfApps":99909,"searchVolume":23.0,"chance":10,"rank":71},{"keyword":"ir","numberOfApps":16541,"searchVolume":44.0,"chance":34,"rank":6},{"keyword":"irecarga","numberOfApps":205,"searchVolume":36.0,"chance":40,"rank":6},{"keyword":"juntar dinheiro","numberOfApps":1448,"searchVolume":34.0,"chance":45,"rank":6},{"keyword":"m","numberOfApps":7287,"searchVolume":58.0,"chance":55,"rank":25},{"keyword":"mercado","numberOfApps":1168,"searchVolume":56.0,"chance":22,"rank":2},{"keyword":"mercado da bola","numberOfApps":100,"searchVolume":56.0,"chance":41,"rank":5},{"keyword":"mercado financeiro","numberOfApps":1127,"searchVolume":42.0,"chance":29,"rank":10},{"keyword":"mercadolibre","numberOfApps":149,"searchVolume":51.0,"chance":17,"rank":2},{"keyword":"mercados","numberOfApps":2168,"searchVolume":51.0,"chance":35,"rank":14},{"keyword":"meu dinheiro","numberOfApps":1456,"searchVolume":38.0,"chance":48,"rank":18},{"keyword":"minha conta","numberOfApps":43,"searchVolume":51.0,"chance":32,"rank":5},{"keyword":"o mercado","numberOfApps":49,"searchVolume":33.0,"chance":48,"rank":1},{"keyword":"of","numberOfApps":5920,"searchVolume":41.0,"chance":23,"rank":8},{"keyword":"oi recarga","numberOfApps":549,"searchVolume":41.0,"chance":38,"rank":6},{"keyword":"or","numberOfApps":13575,"searchVolume":42.0,"chance":42,"rank":7},{"keyword":"organizador de contas","numberOfApps":327,"searchVolume":34.0,"chance":50,"rank":8},{"keyword":"organizar contas","numberOfApps":275,"searchVolume":28.0,"chance":54,"rank":7},{"keyword":"pag seguro","numberOfApps":30,"searchVolume":62.0,"chance":36,"rank":4},{"keyword":"pagamento","numberOfApps":549,"searchVolume":46.0,"chance":34,"rank":3},{"keyword":"pagamento app","numberOfApps":549,"searchVolume":15.0,"chance":35,"rank":2},{"keyword":"pagamento de boleto","numberOfApps":27,"searchVolume":31.0,"chance":53,"rank":2},{"keyword":"pagamento dinheiro","numberOfApps":47,"searchVolume":21.0,"chance":38,"rank":2},{"keyword":"pagamento pagamento","numberOfApps":547,"searchVolume":24.0,"chance":35,"rank":3},{"keyword":"pagar","numberOfApps":220,"searchVolume":43.0,"chance":41,"rank":7},{"keyword":"pagar contas","numberOfApps":468,"searchVolume":33.0,"chance":36,"rank":3},{"keyword":"pagseguro","numberOfApps":33,"searchVolume":62.0,"chance":36,"rank":4},{"keyword":"pay pal","numberOfApps":668,"searchVolume":44.0,"chance":43,"rank":5},{"keyword":"paypal","numberOfApps":661,"searchVolume":56.0,"chance":43,"rank":5},{"keyword":"planilha de contas","numberOfApps":386,"searchVolume":28.0,"chance":50,"rank":12},{"keyword":"ponto certo bilhete unico","numberOfApps":26,"searchVolume":31.0,"chance":54,"rank":4},{"keyword":"por gratis","numberOfApps":226496,"searchVolume":61.0,"chance":5,"rank":221},{"keyword":"por grátis","numberOfApps":226441,"searchVolume":23.0,"chance":5,"rank":221},{"keyword":"pr","numberOfApps":18716,"searchVolume":49.0,"chance":36,"rank":9},{"keyword":"qa","numberOfApps":15006,"searchVolume":41.0,"chance":43,"rank":6},{"keyword":"qr","numberOfApps":5710,"searchVolume":41.0,"chance":58,"rank":51},{"keyword":"recarga","numberOfApps":206,"searchVolume":44.0,"chance":41,"rank":4},{"keyword":"recarga celular","numberOfApps":49,"searchVolume":38.0,"chance":47,"rank":2},{"keyword":"recarga de celular","numberOfApps":205,"searchVolume":38.0,"chance":39,"rank":2},{"keyword":"recargapay","numberOfApps":207,"searchVolume":51.0,"chance":35,"rank":2},{"keyword":"recarregar","numberOfApps":216,"searchVolume":38.0,"chance":42,"rank":3},{"keyword":"saldo","numberOfApps":419,"searchVolume":43.0,"chance":35,"rank":6},{"keyword":"seu","numberOfApps":6897,"searchVolume":44.0,"chance":42,"rank":10},{"keyword":"unico","numberOfApps":2859,"searchVolume":42.0,"chance":44,"rank":6},{"keyword":"vale","numberOfApps":1813,"searchVolume":52.0,"chance":44,"rank":6},{"keyword":"ver saldo","numberOfApps":323,"searchVolume":31.0,"chance":32,"rank":4},{"keyword":"único","numberOfApps":319,"searchVolume":38.0,"chance":46,"rank":4}],"success":true,"status":"success"}