{"data":[{"keyword":"adesivo","numberOfApps":1694,"searchVolume":5.0,"chance":42,"rank":6},{"keyword":"adesivos","numberOfApps":962,"searchVolume":5.0,"chance":51,"rank":5},{"keyword":"alvo","numberOfApps":1215,"searchVolume":5.0,"chance":56,"rank":6},{"keyword":"animated backgrounds","numberOfApps":5619,"searchVolume":5.0,"chance":49,"rank":10},{"keyword":"animoji","numberOfApps":31607,"searchVolume":44.0,"chance":59,"rank":16},{"keyword":"app","numberOfApps":12227,"searchVolume":25.0,"chance":48,"rank":71},{"keyword":"apps","numberOfApps":12355,"searchVolume":13.0,"chance":50,"rank":76},{"keyword":"arco","numberOfApps":3294,"searchVolume":5.0,"chance":58,"rank":5},{"keyword":"arco iris","numberOfApps":236,"searchVolume":5.0,"chance":74,"rank":3},{"keyword":"arco-íris","numberOfApps":236,"searchVolume":5.0,"chance":73,"rank":2},{"keyword":"autocolante","numberOfApps":80,"searchVolume":36.0,"chance":66,"rank":1},{"keyword":"background","numberOfApps":6196,"searchVolume":19.0,"chance":47,"rank":22},{"keyword":"backgrounds","numberOfApps":6212,"searchVolume":5.0,"chance":43,"rank":49},{"keyword":"backgrounds.","numberOfApps":6214,"searchVolume":5.0,"chance":42,"rank":41},{"keyword":"chave","numberOfApps":1039,"searchVolume":5.0,"chance":54,"rank":5},{"keyword":"chaves","numberOfApps":19293,"searchVolume":5.0,"chance":22,"rank":29},{"keyword":"cool","numberOfApps":12233,"searchVolume":5.0,"chance":27,"rank":125},{"keyword":"coolest","numberOfApps":12233,"searchVolume":5.0,"chance":27,"rank":124},{"keyword":"criar texto","numberOfApps":1757,"searchVolume":5.0,"chance":37,"rank":21},{"keyword":"custo","numberOfApps":7995,"searchVolume":5.0,"chance":46,"rank":12},{"keyword":"customizar","numberOfApps":1976,"searchVolume":5.0,"chance":51,"rank":3},{"keyword":"de","numberOfApps":184341,"searchVolume":5.0,"chance":29,"rank":212},{"keyword":"design","numberOfApps":26606,"searchVolume":37.0,"chance":33,"rank":29},{"keyword":"design de interiores","numberOfApps":22276,"searchVolume":5.0,"chance":38,"rank":32},{"keyword":"designer","numberOfApps":25223,"searchVolume":5.0,"chance":49,"rank":64},{"keyword":"editar texto","numberOfApps":3849,"searchVolume":5.0,"chance":37,"rank":33},{"keyword":"emoji","numberOfApps":31552,"searchVolume":42.0,"chance":56,"rank":22},{"keyword":"emoji blitz","numberOfApps":31518,"searchVolume":5.0,"chance":60,"rank":15},{"keyword":"enjin","numberOfApps":34627,"searchVolume":5.0,"chance":56,"rank":17},{"keyword":"fif","numberOfApps":7182,"searchVolume":5.0,"chance":39,"rank":29},{"keyword":"fisrt","numberOfApps":66553,"searchVolume":5.0,"chance":54,"rank":35},{"keyword":"fixe","numberOfApps":124,"searchVolume":5.0,"chance":42,"rank":6},{"keyword":"font","numberOfApps":2666,"searchVolume":20.0,"chance":45,"rank":21},{"keyword":"fonte","numberOfApps":2767,"searchVolume":12.0,"chance":50,"rank":17},{"keyword":"fonts","numberOfApps":2668,"searchVolume":58.0,"chance":44,"rank":13},{"keyword":"fãs","numberOfApps":32282,"searchVolume":5.0,"chance":29,"rank":44},{"keyword":"game maker","numberOfApps":19049,"searchVolume":5.0,"chance":35,"rank":62},{"keyword":"gf","numberOfApps":7833,"searchVolume":5.0,"chance":43,"rank":14},{"keyword":"gif","numberOfApps":5432,"searchVolume":35.0,"chance":46,"rank":12},{"keyword":"giff","numberOfApps":5464,"searchVolume":5.0,"chance":45,"rank":12},{"keyword":"gio","numberOfApps":5793,"searchVolume":5.0,"chance":43,"rank":12},{"keyword":"gis","numberOfApps":7050,"searchVolume":5.0,"chance":49,"rank":13},{"keyword":"iphone","numberOfApps":19232,"searchVolume":29.0,"chance":49,"rank":74},{"keyword":"iphone 7","numberOfApps":31858,"searchVolume":5.0,"chance":45,"rank":39},{"keyword":"keyboard backgrounds","numberOfApps":163,"searchVolume":5.0,"chance":62,"rank":3},{"keyword":"laser","numberOfApps":3158,"searchVolume":5.0,"chance":56,"rank":5},{"keyword":"maker","numberOfApps":20462,"searchVolume":5.0,"chance":33,"rank":93},{"keyword":"nove","numberOfApps":9525,"searchVolume":5.0,"chance":35,"rank":31},{"keyword":"novo","numberOfApps":2663,"searchVolume":7.0,"chance":40,"rank":22},{"keyword":"nts","numberOfApps":1365,"searchVolume":5.0,"chance":48,"rank":6},{"keyword":"on","numberOfApps":124903,"searchVolume":5.0,"chance":40,"rank":69},{"keyword":"ont","numberOfApps":55193,"searchVolume":5.0,"chance":55,"rank":30},{"keyword":"phone themes","numberOfApps":672,"searchVolume":5.0,"chance":72,"rank":12},{"keyword":"quick","numberOfApps":32153,"searchVolume":36.0,"chance":34,"rank":65},{"keyword":"r","numberOfApps":683,"searchVolume":5.0,"chance":62,"rank":37},{"keyword":"smile","numberOfApps":5534,"searchVolume":5.0,"chance":51,"rank":8},{"keyword":"sms","numberOfApps":21847,"searchVolume":19.0,"chance":31,"rank":45},{"keyword":"sticker","numberOfApps":48790,"searchVolume":39.0,"chance":36,"rank":28},{"keyword":"super hero","numberOfApps":3784,"searchVolume":5.0,"chance":49,"rank":18},{"keyword":"tap app","numberOfApps":12355,"searchVolume":5.0,"chance":47,"rank":76},{"keyword":"teclado","numberOfApps":645,"searchVolume":37.0,"chance":47,"rank":4},{"keyword":"teclado colorido","numberOfApps":643,"searchVolume":5.0,"chance":52,"rank":5},{"keyword":"teclado emoji iphone","numberOfApps":31545,"searchVolume":5.0,"chance":49,"rank":17},{"keyword":"teclado gif","numberOfApps":6009,"searchVolume":5.0,"chance":44,"rank":4},{"keyword":"teclado go","numberOfApps":643,"searchVolume":5.0,"chance":49,"rank":8},{"keyword":"teclado google","numberOfApps":643,"searchVolume":5.0,"chance":48,"rank":6},{"keyword":"teclado iphone","numberOfApps":643,"searchVolume":40.0,"chance":47,"rank":9},{"keyword":"teclado personalizado","numberOfApps":643,"searchVolume":24.0,"chance":50,"rank":9},{"keyword":"teclado swiftkey","numberOfApps":645,"searchVolume":17.0,"chance":48,"rank":4},{"keyword":"telas","numberOfApps":972,"searchVolume":5.0,"chance":42,"rank":8},{"keyword":"tema","numberOfApps":3387,"searchVolume":5.0,"chance":44,"rank":12},{"keyword":"tema iphone","numberOfApps":4071,"searchVolume":5.0,"chance":41,"rank":15},{"keyword":"temas","numberOfApps":450,"searchVolume":18.0,"chance":48,"rank":15},{"keyword":"temas de teclado","numberOfApps":104,"searchVolume":5.0,"chance":71,"rank":4},{"keyword":"temas iphone","numberOfApps":431,"searchVolume":28.0,"chance":44,"rank":5},{"keyword":"temos","numberOfApps":1629,"searchVolume":5.0,"chance":43,"rank":11},{"keyword":"text","numberOfApps":23209,"searchVolume":5.0,"chance":35,"rank":64},{"keyword":"texto","numberOfApps":24113,"searchVolume":6.0,"chance":68,"rank":56},{"keyword":"texto fotos","numberOfApps":1786,"searchVolume":5.0,"chance":36,"rank":30},{"keyword":"theme","numberOfApps":4552,"searchVolume":5.0,"chance":50,"rank":16},{"keyword":"tron","numberOfApps":449,"searchVolume":5.0,"chance":68,"rank":4},{"keyword":"txt","numberOfApps":24137,"searchVolume":5.0,"chance":35,"rank":35}],"success":true,"status":"success"}