{"data":[{"keyword":"#me","numberOfApps":23459,"searchVolume":44.0,"chance":75,"rank":104},{"keyword":"\u0026 lifestyle","numberOfApps":109246,"searchVolume":31.0,"chance":68,"rank":147},{"keyword":"12 minute athlete","numberOfApps":462,"searchVolume":5.0,"chance":74,"rank":95},{"keyword":"3","numberOfApps":685,"searchVolume":51.0,"chance":59,"rank":1},{"keyword":"30","numberOfApps":3248,"searchVolume":9.0,"chance":65,"rank":1},{"keyword":"30 da","numberOfApps":730,"searchVolume":5.0,"chance":65,"rank":1},{"keyword":"30 day ab challenge","numberOfApps":196,"searchVolume":39.0,"chance":71,"rank":16},{"keyword":"30 day abs challenge","numberOfApps":210,"searchVolume":5.0,"chance":60,"rank":3},{"keyword":"30 day abs workout challenge","numberOfApps":107,"searchVolume":5.0,"chance":79,"rank":12},{"keyword":"30 day fitness","numberOfApps":589,"searchVolume":38.0,"chance":55,"rank":1},{"keyword":"30 day fitness challenge","numberOfApps":440,"searchVolume":52.0,"chance":56,"rank":1},{"keyword":"30 day fitness challenge free","numberOfApps":251,"searchVolume":19.0,"chance":61,"rank":3},{"keyword":"30 day fitness challenges","numberOfApps":440,"searchVolume":5.0,"chance":80,"rank":23},{"keyword":"30 days ab challenge","numberOfApps":122,"searchVolume":5.0,"chance":80,"rank":19},{"keyword":"30 days free","numberOfApps":415,"searchVolume":5.0,"chance":53,"rank":4},{"keyword":"30+","numberOfApps":3250,"searchVolume":9.0,"chance":59,"rank":1},{"keyword":"5 minute workout","numberOfApps":12289,"searchVolume":5.0,"chance":76,"rank":232},{"keyword":"5k runner","numberOfApps":167,"searchVolume":24.0,"chance":54,"rank":21},{"keyword":"5x5","numberOfApps":338,"searchVolume":21.0,"chance":55,"rank":3},{"keyword":"7 min workout","numberOfApps":521,"searchVolume":10.0,"chance":56,"rank":6},{"keyword":"7 minute","numberOfApps":634,"searchVolume":5.0,"chance":80,"rank":148},{"keyword":"7 minute abs","numberOfApps":2300,"searchVolume":5.0,"chance":82,"rank":103},{"keyword":"7 minute women","numberOfApps":133,"searchVolume":7.0,"chance":59,"rank":5},{"keyword":"7 minute workout","numberOfApps":597,"searchVolume":37.0,"chance":79,"rank":170},{"keyword":"7 minute workout challenge","numberOfApps":485,"searchVolume":5.0,"chance":76,"rank":118},{"keyword":"7 minute workout for women","numberOfApps":471,"searchVolume":5.0,"chance":74,"rank":135},{"keyword":"7 minute workout free","numberOfApps":300,"searchVolume":46.0,"chance":47,"rank":4},{"keyword":"7 minutes workout","numberOfApps":607,"searchVolume":20.0,"chance":76,"rank":107},{"keyword":"7m women","numberOfApps":36,"searchVolume":23.0,"chance":47,"rank":4},{"keyword":"7m workout","numberOfApps":506,"searchVolume":26.0,"chance":66,"rank":45},{"keyword":"8 fit","numberOfApps":106,"searchVolume":27.0,"chance":45,"rank":5},{"keyword":"8 mins abs workout","numberOfApps":1354,"searchVolume":5.0,"chance":79,"rank":117},{"keyword":"8 minutes abs workout","numberOfApps":1100,"searchVolume":5.0,"chance":79,"rank":104},{"keyword":"8fit","numberOfApps":78,"searchVolume":43.0,"chance":45,"rank":4},{"keyword":"ab","numberOfApps":14917,"searchVolume":24.0,"chance":65,"rank":40},{"keyword":"ab blast","numberOfApps":473,"searchVolume":14.0,"chance":68,"rank":50},{"keyword":"ab challenge","numberOfApps":405,"searchVolume":23.0,"chance":54,"rank":3},{"keyword":"ab exercises","numberOfApps":573,"searchVolume":5.0,"chance":70,"rank":61},{"keyword":"ab fitness","numberOfApps":1585,"searchVolume":5.0,"chance":61,"rank":11},{"keyword":"ab workout","numberOfApps":1589,"searchVolume":37.0,"chance":56,"rank":5},{"keyword":"ab workout free","numberOfApps":759,"searchVolume":5.0,"chance":54,"rank":7},{"keyword":"ab workouts","numberOfApps":528,"searchVolume":7.0,"chance":60,"rank":7},{"keyword":"ab workouts free","numberOfApps":330,"searchVolume":5.0,"chance":57,"rank":7},{"keyword":"aba","numberOfApps":2549,"searchVolume":13.0,"chance":72,"rank":67},{"keyword":"abb","numberOfApps":13991,"searchVolume":5.0,"chance":83,"rank":26},{"keyword":"abb workout","numberOfApps":1430,"searchVolume":27.0,"chance":51,"rank":5},{"keyword":"abbs workout","numberOfApps":1100,"searchVolume":5.0,"chance":74,"rank":30},{"keyword":"abdos","numberOfApps":1956,"searchVolume":5.0,"chance":71,"rank":60},{"keyword":"abs","numberOfApps":1897,"searchVolume":40.0,"chance":52,"rank":9},{"keyword":"abs \u0026 core","numberOfApps":317,"searchVolume":5.0,"chance":61,"rank":10},{"keyword":"abs and core","numberOfApps":328,"searchVolume":21.0,"chance":66,"rank":11},{"keyword":"abs cbn","numberOfApps":326,"searchVolume":5.0,"chance":72,"rank":14},{"keyword":"abs challenge","numberOfApps":392,"searchVolume":5.0,"chance":84,"rank":51},{"keyword":"abs exercises","numberOfApps":840,"searchVolume":5.0,"chance":79,"rank":37},{"keyword":"abs workout","numberOfApps":1556,"searchVolume":41.0,"chance":56,"rank":8},{"keyword":"abs workout - 7 minutes","numberOfApps":154,"searchVolume":5.0,"chance":80,"rank":26},{"keyword":"abs workout for women","numberOfApps":1147,"searchVolume":5.0,"chance":83,"rank":143},{"keyword":"abs workout free","numberOfApps":744,"searchVolume":18.0,"chance":56,"rank":9},{"keyword":"abs workouts","numberOfApps":1245,"searchVolume":5.0,"chance":77,"rank":187},{"keyword":"activity","numberOfApps":9098,"searchVolume":45.0,"chance":64,"rank":16},{"keyword":"activity app","numberOfApps":9098,"searchVolume":25.0,"chance":50,"rank":9},{"keyword":"activity tracker","numberOfApps":1266,"searchVolume":31.0,"chance":70,"rank":57},{"keyword":"adrian james 6 pack abs workout","numberOfApps":1104,"searchVolume":5.0,"chance":72,"rank":100},{"keyword":"ads","numberOfApps":7482,"searchVolume":23.0,"chance":71,"rank":56},{"keyword":"app cricket","numberOfApps":32736,"searchVolume":5.0,"chance":29,"rank":38},{"keyword":"app exercise","numberOfApps":13351,"searchVolume":5.0,"chance":43,"rank":13},{"keyword":"app exercises","numberOfApps":13349,"searchVolume":5.0,"chance":38,"rank":12},{"keyword":"app planner","numberOfApps":7457,"searchVolume":5.0,"chance":42,"rank":18},{"keyword":"app tracker","numberOfApps":30344,"searchVolume":5.0,"chance":42,"rank":7},{"keyword":"app trainer","numberOfApps":64975,"searchVolume":5.0,"chance":25,"rank":55},{"keyword":"app training","numberOfApps":34579,"searchVolume":5.0,"chance":31,"rank":20},{"keyword":"apple health","numberOfApps":171509,"searchVolume":36.0,"chance":51,"rank":106},{"keyword":"apple health app","numberOfApps":166604,"searchVolume":39.0,"chance":46,"rank":48},{"keyword":"applications","numberOfApps":5331,"searchVolume":5.0,"chance":34,"rank":43},{"keyword":"apps tracking","numberOfApps":40882,"searchVolume":5.0,"chance":31,"rank":36},{"keyword":"appsfire","numberOfApps":23860,"searchVolume":5.0,"chance":82,"rank":105},{"keyword":"arms","numberOfApps":9444,"searchVolume":15.0,"chance":84,"rank":64},{"keyword":"arms workout","numberOfApps":1470,"searchVolume":12.0,"chance":71,"rank":160},{"keyword":"at home","numberOfApps":931,"searchVolume":15.0,"chance":83,"rank":85},{"keyword":"at home workout","numberOfApps":12392,"searchVolume":5.0,"chance":70,"rank":140},{"keyword":"athome","numberOfApps":909,"searchVolume":13.0,"chance":82,"rank":85},{"keyword":"beginner workout","numberOfApps":12683,"searchVolume":5.0,"chance":78,"rank":110},{"keyword":"beginners workout","numberOfApps":12666,"searchVolume":5.0,"chance":70,"rank":111},{"keyword":"belly fat","numberOfApps":376,"searchVolume":5.0,"chance":75,"rank":29},{"keyword":"bending spoons","numberOfApps":72,"searchVolume":5.0,"chance":52,"rank":1},{"keyword":"betterme: weight loss workouts","numberOfApps":32,"searchVolume":8.0,"chance":52,"rank":10},{"keyword":"bit","numberOfApps":4314,"searchVolume":37.0,"chance":60,"rank":25},{"keyword":"bity","numberOfApps":4363,"searchVolume":5.0,"chance":74,"rank":19},{"keyword":"bmi tracker","numberOfApps":1981,"searchVolume":5.0,"chance":62,"rank":11},{"keyword":"body weight workouts","numberOfApps":988,"searchVolume":5.0,"chance":78,"rank":78},{"keyword":"bodyweight workouts","numberOfApps":976,"searchVolume":5.0,"chance":53,"rank":5},{"keyword":"business planner","numberOfApps":7672,"searchVolume":5.0,"chance":59,"rank":192},{"keyword":"butt workout","numberOfApps":696,"searchVolume":29.0,"chance":67,"rank":5},{"keyword":"c25k nhs","numberOfApps":117,"searchVolume":8.0,"chance":47,"rank":10},{"keyword":"calender planner","numberOfApps":7535,"searchVolume":21.0,"chance":55,"rank":23},{"keyword":"cardiio","numberOfApps":33,"searchVolume":5.0,"chance":53,"rank":5},{"keyword":"challange","numberOfApps":354,"searchVolume":5.0,"chance":85,"rank":16},{"keyword":"challenge","numberOfApps":17653,"searchVolume":23.0,"chance":73,"rank":139},{"keyword":"challenger","numberOfApps":17827,"searchVolume":5.0,"chance":84,"rank":33},{"keyword":"challenges","numberOfApps":17577,"searchVolume":12.0,"chance":82,"rank":199},{"keyword":"clean my iphone","numberOfApps":58675,"searchVolume":5.0,"chance":41,"rank":246},{"keyword":"clue - period tracker","numberOfApps":363,"searchVolume":30.0,"chance":61,"rank":37},{"keyword":"coach to 5k","numberOfApps":143,"searchVolume":43.0,"chance":57,"rank":26},{"keyword":"coach to 5k nhs","numberOfApps":132,"searchVolume":7.0,"chance":58,"rank":21},{"keyword":"couch","numberOfApps":7055,"searchVolume":14.0,"chance":49,"rank":12},{"keyword":"couch potato to 5k!","numberOfApps":35,"searchVolume":12.0,"chance":48,"rank":11},{"keyword":"couch to 5 k","numberOfApps":139,"searchVolume":17.0,"chance":60,"rank":36},{"keyword":"couch to 5k","numberOfApps":132,"searchVolume":65.0,"chance":57,"rank":37},{"keyword":"couch to 5k bbc","numberOfApps":25,"searchVolume":12.0,"chance":42,"rank":8},{"keyword":"couch to 5k free","numberOfApps":73,"searchVolume":27.0,"chance":43,"rank":9},{"keyword":"couch to 5k free nhs","numberOfApps":65,"searchVolume":45.0,"chance":43,"rank":9},{"keyword":"couch to 5k nhs","numberOfApps":131,"searchVolume":37.0,"chance":61,"rank":22},{"keyword":"couchto5k","numberOfApps":132,"searchVolume":5.0,"chance":61,"rank":23},{"keyword":"daily ab workout","numberOfApps":1411,"searchVolume":18.0,"chance":61,"rank":155},{"keyword":"daily fitness","numberOfApps":155662,"searchVolume":5.0,"chance":62,"rank":205},{"keyword":"daily planner","numberOfApps":1081,"searchVolume":35.0,"chance":54,"rank":11},{"keyword":"daily workouts fitness trainer","numberOfApps":303,"searchVolume":12.0,"chance":60,"rank":26},{"keyword":"date planner","numberOfApps":7247,"searchVolume":5.0,"chance":75,"rank":130},{"keyword":"day","numberOfApps":19909,"searchVolume":16.0,"chance":84,"rank":68},{"keyword":"day day","numberOfApps":19814,"searchVolume":5.0,"chance":61,"rank":10},{"keyword":"day planner","numberOfApps":996,"searchVolume":32.0,"chance":51,"rank":7},{"keyword":"day schedule","numberOfApps":658,"searchVolume":5.0,"chance":75,"rank":11},{"keyword":"day tracker","numberOfApps":804,"searchVolume":5.0,"chance":69,"rank":9},{"keyword":"days","numberOfApps":19846,"searchVolume":23.0,"chance":44,"rank":31},{"keyword":"diet and exercise","numberOfApps":17590,"searchVolume":5.0,"chance":75,"rank":173},{"keyword":"diet app","numberOfApps":17726,"searchVolume":33.0,"chance":44,"rank":17},{"keyword":"digital planner","numberOfApps":7247,"searchVolume":5.0,"chance":65,"rank":127},{"keyword":"easy workout","numberOfApps":13334,"searchVolume":5.0,"chance":68,"rank":109},{"keyword":"excercise","numberOfApps":13474,"searchVolume":26.0,"chance":47,"rank":5},{"keyword":"excercise app free","numberOfApps":6565,"searchVolume":5.0,"chance":47,"rank":8},{"keyword":"excercise challenge","numberOfApps":629,"searchVolume":5.0,"chance":57,"rank":3},{"keyword":"excersise app","numberOfApps":13354,"searchVolume":5.0,"chance":46,"rank":5},{"keyword":"exercice","numberOfApps":13447,"searchVolume":5.0,"chance":43,"rank":9},{"keyword":"exercice abdos","numberOfApps":13447,"searchVolume":5.0,"chance":41,"rank":11},{"keyword":"exercise","numberOfApps":13355,"searchVolume":38.0,"chance":50,"rank":2},{"keyword":"exercise app","numberOfApps":13346,"searchVolume":46.0,"chance":49,"rank":5},{"keyword":"exercise apps","numberOfApps":13347,"searchVolume":18.0,"chance":46,"rank":3},{"keyword":"exercise bike","numberOfApps":11376,"searchVolume":14.0,"chance":86,"rank":55},{"keyword":"exercise calorie calculator","numberOfApps":11571,"searchVolume":5.0,"chance":88,"rank":82},{"keyword":"exercise diary","numberOfApps":11382,"searchVolume":5.0,"chance":90,"rank":70},{"keyword":"exercise exercises","numberOfApps":13272,"searchVolume":5.0,"chance":73,"rank":134},{"keyword":"exercise for less","numberOfApps":11388,"searchVolume":29.0,"chance":53,"rank":4},{"keyword":"exercise for women","numberOfApps":11506,"searchVolume":5.0,"chance":87,"rank":88},{"keyword":"exercise free","numberOfApps":6487,"searchVolume":5.0,"chance":46,"rank":15},{"keyword":"exercise games","numberOfApps":12086,"searchVolume":9.0,"chance":77,"rank":117},{"keyword":"exercise log","numberOfApps":981,"searchVolume":5.0,"chance":78,"rank":67},{"keyword":"exercise map","numberOfApps":13253,"searchVolume":5.0,"chance":66,"rank":52},{"keyword":"exercise plan","numberOfApps":11466,"searchVolume":5.0,"chance":90,"rank":23},{"keyword":"exercise planner","numberOfApps":11725,"searchVolume":16.0,"chance":80,"rank":6},{"keyword":"exercise timer","numberOfApps":11454,"searchVolume":23.0,"chance":47,"rank":9},{"keyword":"exercise tracker","numberOfApps":11901,"searchVolume":24.0,"chance":45,"rank":4},{"keyword":"exercise tracking","numberOfApps":1935,"searchVolume":5.0,"chance":69,"rank":10},{"keyword":"exercise trainer","numberOfApps":5652,"searchVolume":5.0,"chance":75,"rank":30},{"keyword":"exercise training","numberOfApps":5624,"searchVolume":5.0,"chance":63,"rank":27},{"keyword":"exercise.com","numberOfApps":13250,"searchVolume":5.0,"chance":73,"rank":51},{"keyword":"exercise4less","numberOfApps":13263,"searchVolume":15.0,"chance":53,"rank":4},{"keyword":"exercises","numberOfApps":13353,"searchVolume":7.0,"chance":54,"rank":6},{"keyword":"exercises app","numberOfApps":13349,"searchVolume":5.0,"chance":43,"rank":6},{"keyword":"exercises exercise","numberOfApps":13272,"searchVolume":5.0,"chance":73,"rank":133},{"keyword":"exercises training","numberOfApps":5622,"searchVolume":5.0,"chance":72,"rank":39},{"keyword":"exercising","numberOfApps":11408,"searchVolume":5.0,"chance":60,"rank":43},{"keyword":"exercize","numberOfApps":13259,"searchVolume":5.0,"chance":68,"rank":13},{"keyword":"fabletics","numberOfApps":73,"searchVolume":30.0,"chance":53,"rank":7},{"keyword":"fare planner","numberOfApps":3970,"searchVolume":5.0,"chance":40,"rank":19},{"keyword":"fast exercise","numberOfApps":11809,"searchVolume":6.0,"chance":83,"rank":78},{"keyword":"female fitness","numberOfApps":155622,"searchVolume":23.0,"chance":46,"rank":4},{"keyword":"female workout","numberOfApps":12430,"searchVolume":5.0,"chance":74,"rank":120},{"keyword":"fit","numberOfApps":16532,"searchVolume":39.0,"chance":47,"rank":5},{"keyword":"fit app","numberOfApps":160068,"searchVolume":17.0,"chance":42,"rank":2},{"keyword":"fit bit","numberOfApps":791,"searchVolume":43.0,"chance":47,"rank":14},{"keyword":"fit bit app","numberOfApps":209,"searchVolume":39.0,"chance":41,"rank":10},{"keyword":"fit challenges","numberOfApps":363,"searchVolume":5.0,"chance":65,"rank":14},{"keyword":"fit coach","numberOfApps":306,"searchVolume":26.0,"chance":55,"rank":6},{"keyword":"fit health","numberOfApps":7088,"searchVolume":5.0,"chance":53,"rank":69},{"keyword":"fit it","numberOfApps":325,"searchVolume":5.0,"chance":95,"rank":126},{"keyword":"fit4less","numberOfApps":156320,"searchVolume":5.0,"chance":35,"rank":27},{"keyword":"fitapp","numberOfApps":750,"searchVolume":5.0,"chance":82,"rank":22},{"keyword":"fitbit","numberOfApps":192,"searchVolume":72.0,"chance":72,"rank":71},{"keyword":"fitbit app","numberOfApps":1064,"searchVolume":56.0,"chance":42,"rank":9},{"keyword":"fitbit app for ipad","numberOfApps":163,"searchVolume":34.0,"chance":46,"rank":14},{"keyword":"fitbit app for ipad free","numberOfApps":96,"searchVolume":44.0,"chance":45,"rank":16},{"keyword":"fitbit app for iphone","numberOfApps":165,"searchVolume":5.0,"chance":64,"rank":61},{"keyword":"fitbit apps","numberOfApps":167,"searchVolume":13.0,"chance":55,"rank":8},{"keyword":"fitbit blaze","numberOfApps":141,"searchVolume":23.0,"chance":70,"rank":23},{"keyword":"fitbit free","numberOfApps":83,"searchVolume":5.0,"chance":50,"rank":5},{"keyword":"fitbit set up","numberOfApps":140,"searchVolume":5.0,"chance":43,"rank":10},{"keyword":"fitbit setup","numberOfApps":140,"searchVolume":21.0,"chance":43,"rank":10},{"keyword":"fitbit tracker","numberOfApps":405,"searchVolume":14.0,"chance":67,"rank":71},{"keyword":"fitbod","numberOfApps":41,"searchVolume":36.0,"chance":54,"rank":8},{"keyword":"fitbod weight lifting tracker","numberOfApps":24,"searchVolume":19.0,"chance":58,"rank":9},{"keyword":"fitnes","numberOfApps":156359,"searchVolume":15.0,"chance":43,"rank":1},{"keyword":"fitness","numberOfApps":156283,"searchVolume":58.0,"chance":55,"rank":2},{"keyword":"fitness  workouts","numberOfApps":156308,"searchVolume":5.0,"chance":53,"rank":7},{"keyword":"fitness 22","numberOfApps":60,"searchVolume":11.0,"chance":49,"rank":3},{"keyword":"fitness app","numberOfApps":156349,"searchVolume":43.0,"chance":43,"rank":1},{"keyword":"fitness app free","numberOfApps":90250,"searchVolume":5.0,"chance":41,"rank":6},{"keyword":"fitness apps","numberOfApps":156376,"searchVolume":48.0,"chance":43,"rank":1},{"keyword":"fitness apps for free","numberOfApps":90214,"searchVolume":22.0,"chance":44,"rank":8},{"keyword":"fitness apps for kids","numberOfApps":155668,"searchVolume":12.0,"chance":42,"rank":11},{"keyword":"fitness buddy","numberOfApps":1143,"searchVolume":34.0,"chance":68,"rank":14},{"keyword":"fitness buddy app","numberOfApps":467,"searchVolume":5.0,"chance":50,"rank":7},{"keyword":"fitness buddy+","numberOfApps":466,"searchVolume":34.0,"chance":58,"rank":6},{"keyword":"fitness calendar","numberOfApps":165662,"searchVolume":5.0,"chance":64,"rank":60},{"keyword":"fitness challenge","numberOfApps":1823,"searchVolume":10.0,"chance":50,"rank":2},{"keyword":"fitness challenge 30 days","numberOfApps":440,"searchVolume":5.0,"chance":74,"rank":2},{"keyword":"fitness coach","numberOfApps":155618,"searchVolume":5.0,"chance":65,"rank":42},{"keyword":"fitness exercise","numberOfApps":10740,"searchVolume":5.0,"chance":66,"rank":4},{"keyword":"fitness exercises","numberOfApps":10762,"searchVolume":5.0,"chance":82,"rank":132},{"keyword":"fitness first","numberOfApps":4853,"searchVolume":31.0,"chance":79,"rank":21},{"keyword":"fitness fitness","numberOfApps":156261,"searchVolume":5.0,"chance":46,"rank":12},{"keyword":"fitness food","numberOfApps":155621,"searchVolume":5.0,"chance":63,"rank":15},{"keyword":"fitness for girls","numberOfApps":155648,"searchVolume":5.0,"chance":58,"rank":3},{"keyword":"fitness free","numberOfApps":90254,"searchVolume":20.0,"chance":42,"rank":7},{"keyword":"fitness health","numberOfApps":152770,"searchVolume":5.0,"chance":51,"rank":4},{"keyword":"fitness lifestyle","numberOfApps":33765,"searchVolume":5.0,"chance":77,"rank":10},{"keyword":"fitness loose weight","numberOfApps":156,"searchVolume":5.0,"chance":75,"rank":7},{"keyword":"fitness magazine","numberOfApps":155597,"searchVolume":5.0,"chance":71,"rank":16},{"keyword":"fitness nike","numberOfApps":155595,"searchVolume":5.0,"chance":42,"rank":11},{"keyword":"fitness pal","numberOfApps":155594,"searchVolume":37.0,"chance":47,"rank":2},{"keyword":"fitness planner","numberOfApps":7286,"searchVolume":14.0,"chance":53,"rank":4},{"keyword":"fitness point","numberOfApps":155597,"searchVolume":18.0,"chance":76,"rank":11},{"keyword":"fitness pro","numberOfApps":156304,"searchVolume":5.0,"chance":76,"rank":19},{"keyword":"fitness program","numberOfApps":155620,"searchVolume":9.0,"chance":67,"rank":6},{"keyword":"fitness routine","numberOfApps":155614,"searchVolume":5.0,"chance":77,"rank":42},{"keyword":"fitness tracker","numberOfApps":155662,"searchVolume":40.0,"chance":43,"rank":8},{"keyword":"fitness tracker app","numberOfApps":8132,"searchVolume":16.0,"chance":43,"rank":9},{"keyword":"fitness trainer","numberOfApps":19255,"searchVolume":5.0,"chance":59,"rank":8},{"keyword":"fitness training","numberOfApps":17414,"searchVolume":5.0,"chance":48,"rank":4},{"keyword":"fitness women","numberOfApps":155613,"searchVolume":5.0,"chance":62,"rank":52},{"keyword":"fitness workout","numberOfApps":156358,"searchVolume":29.0,"chance":48,"rank":6},{"keyword":"fitness workouts","numberOfApps":156308,"searchVolume":5.0,"chance":53,"rank":7},{"keyword":"fitness22","numberOfApps":60,"searchVolume":5.0,"chance":50,"rank":4},{"keyword":"fitnessbuddy","numberOfApps":447,"searchVolume":5.0,"chance":77,"rank":14},{"keyword":"fitnesspal","numberOfApps":156322,"searchVolume":24.0,"chance":41,"rank":2},{"keyword":"fitness’","numberOfApps":156300,"searchVolume":58.0,"chance":54,"rank":2},{"keyword":"fittness pal","numberOfApps":292,"searchVolume":5.0,"chance":63,"rank":7},{"keyword":"fotbit","numberOfApps":140,"searchVolume":17.0,"chance":48,"rank":9},{"keyword":"free exercise","numberOfApps":6487,"searchVolume":5.0,"chance":44,"rank":7},{"keyword":"free exercise app","numberOfApps":6245,"searchVolume":26.0,"chance":49,"rank":7},{"keyword":"free exercise apps","numberOfApps":6248,"searchVolume":19.0,"chance":49,"rank":6},{"keyword":"free fit","numberOfApps":5919,"searchVolume":5.0,"chance":46,"rank":3},{"keyword":"free fitbit app","numberOfApps":94,"searchVolume":13.0,"chance":41,"rank":8},{"keyword":"free fitness","numberOfApps":90252,"searchVolume":11.0,"chance":41,"rank":7},{"keyword":"free fitness apps","numberOfApps":88990,"searchVolume":39.0,"chance":43,"rank":7},{"keyword":"free health","numberOfApps":96923,"searchVolume":5.0,"chance":37,"rank":56},{"keyword":"free health app","numberOfApps":96921,"searchVolume":13.0,"chance":40,"rank":23},{"keyword":"free heath","numberOfApps":112030,"searchVolume":5.0,"chance":31,"rank":92},{"keyword":"free letics","numberOfApps":9784,"searchVolume":5.0,"chance":56,"rank":7},{"keyword":"free mobile tracker","numberOfApps":18320,"searchVolume":5.0,"chance":38,"rank":36},{"keyword":"free nappies","numberOfApps":100504,"searchVolume":5.0,"chance":16,"rank":163},{"keyword":"free tracker","numberOfApps":18319,"searchVolume":10.0,"chance":42,"rank":34},{"keyword":"free tracker app","numberOfApps":18319,"searchVolume":5.0,"chance":33,"rank":37},{"keyword":"free training","numberOfApps":18575,"searchVolume":5.0,"chance":45,"rank":6},{"keyword":"free workout","numberOfApps":106958,"searchVolume":16.0,"chance":43,"rank":7},{"keyword":"free workout apps","numberOfApps":89080,"searchVolume":23.0,"chance":46,"rank":6},{"keyword":"free workouts","numberOfApps":7274,"searchVolume":5.0,"chance":47,"rank":7},{"keyword":"freeletics","numberOfApps":72,"searchVolume":44.0,"chance":56,"rank":7},{"keyword":"full","numberOfApps":13589,"searchVolume":5.0,"chance":58,"rank":5},{"keyword":"full body workout","numberOfApps":2352,"searchVolume":15.0,"chance":54,"rank":5},{"keyword":"full fitness","numberOfApps":432,"searchVolume":21.0,"chance":58,"rank":4},{"keyword":"full fitness : exercise workout trainer","numberOfApps":427,"searchVolume":5.0,"chance":81,"rank":9},{"keyword":"full training","numberOfApps":419,"searchVolume":5.0,"chance":65,"rank":6},{"keyword":"gain weight","numberOfApps":11128,"searchVolume":21.0,"chance":52,"rank":6},{"keyword":"gaining weight","numberOfApps":11080,"searchVolume":5.0,"chance":82,"rank":171},{"keyword":"get fit","numberOfApps":452,"searchVolume":39.0,"chance":84,"rank":38},{"keyword":"get fit.","numberOfApps":451,"searchVolume":39.0,"chance":77,"rank":20},{"keyword":"getfit","numberOfApps":486,"searchVolume":24.0,"chance":81,"rank":27},{"keyword":"gm","numberOfApps":12641,"searchVolume":18.0,"chance":81,"rank":104},{"keyword":"gym","numberOfApps":12222,"searchVolume":53.0,"chance":46,"rank":5},{"keyword":"gym ab workouts","numberOfApps":140,"searchVolume":5.0,"chance":64,"rank":13},{"keyword":"gym app","numberOfApps":12223,"searchVolume":25.0,"chance":48,"rank":4},{"keyword":"gym at home","numberOfApps":12012,"searchVolume":5.0,"chance":65,"rank":81},{"keyword":"gym buddy","numberOfApps":904,"searchVolume":18.0,"chance":54,"rank":7},{"keyword":"gym coach","numberOfApps":12042,"searchVolume":5.0,"chance":76,"rank":144},{"keyword":"gym diary","numberOfApps":735,"searchVolume":11.0,"chance":57,"rank":6},{"keyword":"gym exercises","numberOfApps":5645,"searchVolume":17.0,"chance":51,"rank":8},{"keyword":"gym fitness","numberOfApps":11160,"searchVolume":5.0,"chance":56,"rank":30},{"keyword":"gym goal","numberOfApps":715,"searchVolume":5.0,"chance":69,"rank":97},{"keyword":"gym life","numberOfApps":12026,"searchVolume":5.0,"chance":62,"rank":25},{"keyword":"gym log","numberOfApps":12313,"searchVolume":20.0,"chance":48,"rank":22},{"keyword":"gym motivation","numberOfApps":14391,"searchVolume":5.0,"chance":80,"rank":59},{"keyword":"gym planner","numberOfApps":5038,"searchVolume":22.0,"chance":56,"rank":7},{"keyword":"gym program","numberOfApps":12041,"searchVolume":6.0,"chance":41,"rank":10},{"keyword":"gym progress","numberOfApps":12017,"searchVolume":5.0,"chance":78,"rank":147},{"keyword":"gym routine","numberOfApps":12038,"searchVolume":17.0,"chance":42,"rank":6},{"keyword":"gym session","numberOfApps":12031,"searchVolume":5.0,"chance":55,"rank":209},{"keyword":"gym tracker","numberOfApps":1768,"searchVolume":30.0,"chance":63,"rank":8},{"keyword":"gym workout","numberOfApps":11201,"searchVolume":46.0,"chance":63,"rank":12},{"keyword":"gym workout programs","numberOfApps":5008,"searchVolume":5.0,"chance":55,"rank":4},{"keyword":"gym workouts","numberOfApps":5318,"searchVolume":13.0,"chance":58,"rank":7},{"keyword":"gym workouts free","numberOfApps":2541,"searchVolume":5.0,"chance":53,"rank":6},{"keyword":"gyms","numberOfApps":12189,"searchVolume":5.0,"chance":63,"rank":112},{"keyword":"gymshark","numberOfApps":30,"searchVolume":61.0,"chance":100,"rank":3},{"keyword":"hard workout","numberOfApps":12303,"searchVolume":5.0,"chance":61,"rank":81},{"keyword":"heal","numberOfApps":166853,"searchVolume":5.0,"chance":86,"rank":61},{"keyword":"health and fitness","numberOfApps":152367,"searchVolume":29.0,"chance":40,"rank":5},{"keyword":"health and fitness apps","numberOfApps":155584,"searchVolume":5.0,"chance":46,"rank":1},{"keyword":"health and safety","numberOfApps":152721,"searchVolume":19.0,"chance":89,"rank":41},{"keyword":"health and social care","numberOfApps":153168,"searchVolume":5.0,"chance":68,"rank":11},{"keyword":"health app","numberOfApps":168688,"searchVolume":52.0,"chance":44,"rank":25},{"keyword":"health app for iphone","numberOfApps":166574,"searchVolume":5.0,"chance":51,"rank":99},{"keyword":"health apps","numberOfApps":166743,"searchVolume":19.0,"chance":38,"rank":20},{"keyword":"health data","numberOfApps":166574,"searchVolume":9.0,"chance":81,"rank":153},{"keyword":"health fit","numberOfApps":7088,"searchVolume":12.0,"chance":54,"rank":68},{"keyword":"health mate","numberOfApps":166571,"searchVolume":29.0,"chance":54,"rank":59},{"keyword":"health tips","numberOfApps":166813,"searchVolume":5.0,"chance":88,"rank":128},{"keyword":"health tracker","numberOfApps":8280,"searchVolume":18.0,"chance":41,"rank":12},{"keyword":"health tracker!","numberOfApps":8184,"searchVolume":18.0,"chance":60,"rank":61},{"keyword":"health unlocked","numberOfApps":166572,"searchVolume":10.0,"chance":51,"rank":99},{"keyword":"health weight","numberOfApps":9766,"searchVolume":5.0,"chance":54,"rank":137},{"keyword":"healthkit","numberOfApps":12929,"searchVolume":5.0,"chance":67,"rank":199},{"keyword":"healthy  planner","numberOfApps":766,"searchVolume":5.0,"chance":54,"rank":30},{"keyword":"healthy app","numberOfApps":168772,"searchVolume":5.0,"chance":37,"rank":48},{"keyword":"healthy lifestyle","numberOfApps":451136,"searchVolume":5.0,"chance":89,"rank":181},{"keyword":"healthy planner","numberOfApps":766,"searchVolume":5.0,"chance":54,"rank":30},{"keyword":"heath","numberOfApps":166947,"searchVolume":13.0,"chance":66,"rank":93},{"keyword":"heigth","numberOfApps":166577,"searchVolume":5.0,"chance":31,"rank":36},{"keyword":"hiit workout","numberOfApps":1567,"searchVolume":31.0,"chance":82,"rank":201},{"keyword":"hit workout","numberOfApps":12359,"searchVolume":13.0,"chance":63,"rank":14},{"keyword":"home fitness","numberOfApps":155637,"searchVolume":5.0,"chance":46,"rank":3},{"keyword":"home workout","numberOfApps":3726,"searchVolume":43.0,"chance":60,"rank":41},{"keyword":"home workout no equipment","numberOfApps":56,"searchVolume":5.0,"chance":72,"rank":13},{"keyword":"hourly planner","numberOfApps":7251,"searchVolume":5.0,"chance":70,"rank":150},{"keyword":"how to loose weight","numberOfApps":225,"searchVolume":12.0,"chance":65,"rank":3},{"keyword":"ifitness","numberOfApps":155592,"searchVolume":9.0,"chance":56,"rank":9},{"keyword":"insanity workout","numberOfApps":12264,"searchVolume":14.0,"chance":75,"rank":177},{"keyword":"intense workout","numberOfApps":12247,"searchVolume":5.0,"chance":73,"rank":191},{"keyword":"iphone tracker","numberOfApps":33691,"searchVolume":31.0,"chance":40,"rank":45},{"keyword":"jefit","numberOfApps":62,"searchVolume":38.0,"chance":54,"rank":6},{"keyword":"la fitness","numberOfApps":155598,"searchVolume":5.0,"chance":65,"rank":18},{"keyword":"lifestyle apps","numberOfApps":451523,"searchVolume":5.0,"chance":31,"rank":146},{"keyword":"lifestyle fitness","numberOfApps":35783,"searchVolume":5.0,"chance":85,"rank":12},{"keyword":"lifestyle planner","numberOfApps":1841,"searchVolume":5.0,"chance":60,"rank":38},{"keyword":"loose","numberOfApps":410,"searchVolume":5.0,"chance":78,"rank":23},{"keyword":"loose it","numberOfApps":314,"searchVolume":32.0,"chance":54,"rank":10},{"keyword":"loose weight","numberOfApps":1646,"searchVolume":35.0,"chance":53,"rank":2},{"keyword":"loose weight free","numberOfApps":78,"searchVolume":11.0,"chance":67,"rank":5},{"keyword":"lose it","numberOfApps":2335,"searchVolume":48.0,"chance":71,"rank":44},{"keyword":"loseit","numberOfApps":2329,"searchVolume":20.0,"chance":75,"rank":50},{"keyword":"losing weight","numberOfApps":3431,"searchVolume":21.0,"chance":44,"rank":9},{"keyword":"map my run","numberOfApps":214,"searchVolume":54.0,"chance":58,"rank":23},{"keyword":"map my run free","numberOfApps":99,"searchVolume":26.0,"chance":50,"rank":17},{"keyword":"mapmyrun","numberOfApps":56,"searchVolume":40.0,"chance":53,"rank":15},{"keyword":"max fitness pro","numberOfApps":155594,"searchVolume":5.0,"chance":90,"rank":40},{"keyword":"me","numberOfApps":23448,"searchVolume":44.0,"chance":41,"rank":16},{"keyword":"meme","numberOfApps":24996,"searchVolume":45.0,"chance":47,"rank":48},{"keyword":"meme app","numberOfApps":24994,"searchVolume":22.0,"chance":48,"rank":45},{"keyword":"minute","numberOfApps":3642,"searchVolume":5.0,"chance":67,"rank":75},{"keyword":"minute 7","numberOfApps":624,"searchVolume":5.0,"chance":73,"rank":109},{"keyword":"minutes","numberOfApps":3640,"searchVolume":5.0,"chance":67,"rank":31},{"keyword":"mobile my","numberOfApps":44153,"searchVolume":5.0,"chance":35,"rank":197},{"keyword":"mobile number tracker","numberOfApps":19439,"searchVolume":5.0,"chance":67,"rank":34},{"keyword":"mobile planner","numberOfApps":7416,"searchVolume":5.0,"chance":57,"rank":124},{"keyword":"mobile tracker","numberOfApps":30361,"searchVolume":18.0,"chance":59,"rank":37},{"keyword":"mobile tracker app","numberOfApps":30319,"searchVolume":5.0,"chance":57,"rank":36},{"keyword":"mobile tracker free","numberOfApps":18316,"searchVolume":7.0,"chance":45,"rank":34},{"keyword":"monitor my weight","numberOfApps":479,"searchVolume":5.0,"chance":51,"rank":9},{"keyword":"monitor your weight","numberOfApps":65,"searchVolume":30.0,"chance":66,"rank":14},{"keyword":"monthly planner","numberOfApps":7344,"searchVolume":5.0,"chance":47,"rank":24},{"keyword":"my","numberOfApps":44167,"searchVolume":38.0,"chance":47,"rank":59},{"keyword":"my apps","numberOfApps":44146,"searchVolume":32.0,"chance":54,"rank":65},{"keyword":"my diet coach","numberOfApps":547,"searchVolume":19.0,"chance":72,"rank":27},{"keyword":"my fitnes pal","numberOfApps":104,"searchVolume":5.0,"chance":72,"rank":16},{"keyword":"my fitness","numberOfApps":3957,"searchVolume":29.0,"chance":60,"rank":3},{"keyword":"my fitness buddy","numberOfApps":520,"searchVolume":5.0,"chance":64,"rank":23},{"keyword":"my fitness pal","numberOfApps":283,"searchVolume":73.0,"chance":57,"rank":2},{"keyword":"my fitness pal app","numberOfApps":289,"searchVolume":39.0,"chance":42,"rank":3},{"keyword":"my fitness pal free","numberOfApps":2395,"searchVolume":34.0,"chance":42,"rank":7},{"keyword":"my fitness pal premium","numberOfApps":104,"searchVolume":5.0,"chance":53,"rank":4},{"keyword":"my fitness trainer","numberOfApps":457,"searchVolume":5.0,"chance":66,"rank":5},{"keyword":"my free","numberOfApps":26302,"searchVolume":5.0,"chance":32,"rank":70},{"keyword":"my mobile","numberOfApps":44166,"searchVolume":5.0,"chance":44,"rank":202},{"keyword":"my plate","numberOfApps":1925,"searchVolume":32.0,"chance":66,"rank":15},{"keyword":"my tracker","numberOfApps":1917,"searchVolume":16.0,"chance":64,"rank":128},{"keyword":"my weight","numberOfApps":642,"searchVolume":29.0,"chance":58,"rank":14},{"keyword":"myapp","numberOfApps":44192,"searchVolume":5.0,"chance":93,"rank":235},{"keyword":"myfirnesspal","numberOfApps":127,"searchVolume":5.0,"chance":43,"rank":2},{"keyword":"myfitness pal","numberOfApps":316,"searchVolume":28.0,"chance":51,"rank":2},{"keyword":"myfitnesspal","numberOfApps":32,"searchVolume":61.0,"chance":42,"rank":8},{"keyword":"myfotnesspal","numberOfApps":127,"searchVolume":5.0,"chance":43,"rank":2},{"keyword":"myplate","numberOfApps":87,"searchVolume":22.0,"chance":67,"rank":16},{"keyword":"nappies free","numberOfApps":100508,"searchVolume":5.0,"chance":18,"rank":163},{"keyword":"nhs 5k","numberOfApps":1339,"searchVolume":5.0,"chance":43,"rank":9},{"keyword":"nike fitness","numberOfApps":64,"searchVolume":19.0,"chance":50,"rank":5},{"keyword":"nike training app","numberOfApps":47,"searchVolume":28.0,"chance":46,"rank":4},{"keyword":"nike training club","numberOfApps":39,"searchVolume":44.0,"chance":47,"rank":3},{"keyword":"online planner","numberOfApps":7248,"searchVolume":5.0,"chance":52,"rank":126},{"keyword":"p tracker lite","numberOfApps":19392,"searchVolume":5.0,"chance":60,"rank":44},{"keyword":"pacer","numberOfApps":208,"searchVolume":43.0,"chance":60,"rank":18},{"keyword":"pal","numberOfApps":1958,"searchVolume":9.0,"chance":49,"rank":73},{"keyword":"people tracker","numberOfApps":19404,"searchVolume":5.0,"chance":57,"rank":78},{"keyword":"personal planner","numberOfApps":7252,"searchVolume":5.0,"chance":71,"rank":160},{"keyword":"pilates workouts","numberOfApps":4157,"searchVolume":5.0,"chance":66,"rank":127},{"keyword":"plan","numberOfApps":25526,"searchVolume":31.0,"chance":50,"rank":55},{"keyword":"planer","numberOfApps":18784,"searchVolume":11.0,"chance":56,"rank":167},{"keyword":"plank challenge","numberOfApps":248,"searchVolume":25.0,"chance":60,"rank":4},{"keyword":"plann","numberOfApps":20625,"searchVolume":34.0,"chance":65,"rank":126},{"keyword":"planner","numberOfApps":7455,"searchVolume":50.0,"chance":50,"rank":11},{"keyword":"planner 5d","numberOfApps":7264,"searchVolume":32.0,"chance":69,"rank":146},{"keyword":"planner app","numberOfApps":7452,"searchVolume":22.0,"chance":46,"rank":11},{"keyword":"planner pro","numberOfApps":7419,"searchVolume":12.0,"chance":52,"rank":129},{"keyword":"planner tracker","numberOfApps":870,"searchVolume":5.0,"chance":54,"rank":57},{"keyword":"planners","numberOfApps":7415,"searchVolume":5.0,"chance":52,"rank":162},{"keyword":"planning","numberOfApps":11454,"searchVolume":20.0,"chance":48,"rank":27},{"keyword":"premium","numberOfApps":7185,"searchVolume":17.0,"chance":68,"rank":41},{"keyword":"ptracker","numberOfApps":30349,"searchVolume":8.0,"chance":46,"rank":39},{"keyword":"pure gym","numberOfApps":122,"searchVolume":60.0,"chance":59,"rank":8},{"keyword":"pure gym app","numberOfApps":62,"searchVolume":29.0,"chance":47,"rank":4},{"keyword":"puregym","numberOfApps":27,"searchVolume":48.0,"chance":47,"rank":5},{"keyword":"quick workout","numberOfApps":13319,"searchVolume":5.0,"chance":63,"rank":136},{"keyword":"samsung health","numberOfApps":166571,"searchVolume":35.0,"chance":70,"rank":60},{"keyword":"seen","numberOfApps":14721,"searchVolume":15.0,"chance":79,"rank":60},{"keyword":"seve","numberOfApps":14269,"searchVolume":5.0,"chance":54,"rank":62},{"keyword":"seven","numberOfApps":14930,"searchVolume":37.0,"chance":49,"rank":7},{"keyword":"seven minute","numberOfApps":634,"searchVolume":5.0,"chance":82,"rank":154},{"keyword":"seven minute workout","numberOfApps":597,"searchVolume":26.0,"chance":62,"rank":8},{"keyword":"slots apps","numberOfApps":12205,"searchVolume":5.0,"chance":57,"rank":32},{"keyword":"spoon","numberOfApps":320,"searchVolume":5.0,"chance":78,"rank":16},{"keyword":"squad","numberOfApps":1753,"searchVolume":37.0,"chance":63,"rank":43},{"keyword":"squast","numberOfApps":604,"searchVolume":5.0,"chance":55,"rank":1},{"keyword":"squat","numberOfApps":606,"searchVolume":20.0,"chance":57,"rank":3},{"keyword":"squat workout","numberOfApps":827,"searchVolume":5.0,"chance":79,"rank":53},{"keyword":"squats","numberOfApps":604,"searchVolume":15.0,"chance":60,"rank":5},{"keyword":"stava","numberOfApps":318,"searchVolume":21.0,"chance":44,"rank":14},{"keyword":"steps app","numberOfApps":4897,"searchVolume":36.0,"chance":44,"rank":15},{"keyword":"stomach workout","numberOfApps":1495,"searchVolume":5.0,"chance":84,"rank":137},{"keyword":"strava","numberOfApps":296,"searchVolume":67.0,"chance":55,"rank":31},{"keyword":"strava cycling","numberOfApps":291,"searchVolume":37.0,"chance":62,"rank":36},{"keyword":"strava free","numberOfApps":211,"searchVolume":27.0,"chance":43,"rank":19},{"keyword":"strava run","numberOfApps":291,"searchVolume":33.0,"chance":54,"rank":29},{"keyword":"strave","numberOfApps":356,"searchVolume":13.0,"chance":43,"rank":17},{"keyword":"strength training","numberOfApps":4382,"searchVolume":23.0,"chance":54,"rank":5},{"keyword":"strong","numberOfApps":1155,"searchVolume":39.0,"chance":61,"rank":7},{"keyword":"strong lifts","numberOfApps":1144,"searchVolume":19.0,"chance":59,"rank":3},{"keyword":"stronglifts","numberOfApps":36,"searchVolume":12.0,"chance":55,"rank":3},{"keyword":"superhero workout","numberOfApps":12229,"searchVolume":5.0,"chance":55,"rank":78},{"keyword":"swork it","numberOfApps":936,"searchVolume":5.0,"chance":50,"rank":7},{"keyword":"sworkit","numberOfApps":122,"searchVolume":38.0,"chance":50,"rank":7},{"keyword":"the fitbit app","numberOfApps":190,"searchVolume":39.0,"chance":43,"rank":9},{"keyword":"the gym","numberOfApps":12195,"searchVolume":53.0,"chance":54,"rank":17},{"keyword":"the gym group","numberOfApps":12038,"searchVolume":40.0,"chance":53,"rank":11},{"keyword":"the health lottery","numberOfApps":166577,"searchVolume":27.0,"chance":86,"rank":46},{"keyword":"the tracker","numberOfApps":30354,"searchVolume":5.0,"chance":44,"rank":209},{"keyword":"time planner","numberOfApps":7242,"searchVolume":5.0,"chance":72,"rank":165},{"keyword":"timepage","numberOfApps":23,"searchVolume":32.0,"chance":51,"rank":6},{"keyword":"tracer","numberOfApps":30684,"searchVolume":5.0,"chance":56,"rank":112},{"keyword":"track my fitness","numberOfApps":155602,"searchVolume":5.0,"chance":50,"rank":5},{"keyword":"track my run","numberOfApps":152,"searchVolume":35.0,"chance":53,"rank":19},{"keyword":"track my weight","numberOfApps":11095,"searchVolume":7.0,"chance":70,"rank":33},{"keyword":"tracker","numberOfApps":30407,"searchVolume":44.0,"chance":40,"rank":25},{"keyword":"tracker app","numberOfApps":30507,"searchVolume":35.0,"chance":39,"rank":27},{"keyword":"tracker application","numberOfApps":30353,"searchVolume":5.0,"chance":44,"rank":207},{"keyword":"tracker free","numberOfApps":18321,"searchVolume":5.0,"chance":37,"rank":35},{"keyword":"tracker health","numberOfApps":8190,"searchVolume":5.0,"chance":50,"rank":131},{"keyword":"tracker screen","numberOfApps":19427,"searchVolume":5.0,"chance":37,"rank":46},{"keyword":"tracking","numberOfApps":40915,"searchVolume":22.0,"chance":38,"rank":29},{"keyword":"tracking app","numberOfApps":40907,"searchVolume":39.0,"chance":37,"rank":44},{"keyword":"tracking apps","numberOfApps":40882,"searchVolume":5.0,"chance":42,"rank":25},{"keyword":"tracking mobile","numberOfApps":40856,"searchVolume":5.0,"chance":50,"rank":81},{"keyword":"trackr","numberOfApps":30524,"searchVolume":26.0,"chance":73,"rank":49},{"keyword":"tracksuits","numberOfApps":19478,"searchVolume":5.0,"chance":39,"rank":25},{"keyword":"trading training","numberOfApps":34580,"searchVolume":5.0,"chance":49,"rank":54},{"keyword":"trainer","numberOfApps":34820,"searchVolume":17.0,"chance":75,"rank":173},{"keyword":"trainer app","numberOfApps":34808,"searchVolume":5.0,"chance":40,"rank":7},{"keyword":"trainer exercise","numberOfApps":5652,"searchVolume":5.0,"chance":75,"rank":61},{"keyword":"trainer exercises","numberOfApps":5650,"searchVolume":5.0,"chance":72,"rank":57},{"keyword":"trainer fee","numberOfApps":18683,"searchVolume":5.0,"chance":30,"rank":24},{"keyword":"trainer france","numberOfApps":18695,"searchVolume":5.0,"chance":30,"rank":24},{"keyword":"trainer french","numberOfApps":18737,"searchVolume":5.0,"chance":30,"rank":24},{"keyword":"trainer training","numberOfApps":34506,"searchVolume":5.0,"chance":53,"rank":125},{"keyword":"training","numberOfApps":34607,"searchVolume":25.0,"chance":43,"rank":3},{"keyword":"training app","numberOfApps":34594,"searchVolume":21.0,"chance":44,"rank":2},{"keyword":"training exercise","numberOfApps":5624,"searchVolume":5.0,"chance":67,"rank":27},{"keyword":"training exercises","numberOfApps":5622,"searchVolume":5.0,"chance":73,"rank":14},{"keyword":"training exercising","numberOfApps":5628,"searchVolume":5.0,"chance":57,"rank":9},{"keyword":"training fee","numberOfApps":18577,"searchVolume":5.0,"chance":32,"rank":20},{"keyword":"training peaks","numberOfApps":27080,"searchVolume":33.0,"chance":65,"rank":26},{"keyword":"training plan","numberOfApps":1200,"searchVolume":5.0,"chance":73,"rank":14},{"keyword":"training program","numberOfApps":1033,"searchVolume":7.0,"chance":78,"rank":19},{"keyword":"training tracker","numberOfApps":1847,"searchVolume":5.0,"chance":71,"rank":15},{"keyword":"training trainer","numberOfApps":34499,"searchVolume":5.0,"chance":53,"rank":125},{"keyword":"trainings","numberOfApps":34584,"searchVolume":5.0,"chance":68,"rank":30},{"keyword":"traker","numberOfApps":30384,"searchVolume":20.0,"chance":57,"rank":33},{"keyword":"triller app","numberOfApps":31224,"searchVolume":5.0,"chance":35,"rank":33},{"keyword":"träning","numberOfApps":34831,"searchVolume":5.0,"chance":53,"rank":8},{"keyword":"veryfitpro","numberOfApps":14,"searchVolume":54.0,"chance":51,"rank":6},{"keyword":"wait","numberOfApps":11634,"searchVolume":5.0,"chance":53,"rank":145},{"keyword":"week planner","numberOfApps":1010,"searchVolume":21.0,"chance":58,"rank":8},{"keyword":"weighing","numberOfApps":11142,"searchVolume":5.0,"chance":69,"rank":30},{"keyword":"weight","numberOfApps":11476,"searchVolume":34.0,"chance":53,"rank":10},{"keyword":"weight calculator","numberOfApps":2391,"searchVolume":5.0,"chance":90,"rank":135},{"keyword":"weight chart","numberOfApps":1623,"searchVolume":5.0,"chance":71,"rank":11},{"keyword":"weight diary","numberOfApps":1998,"searchVolume":17.0,"chance":75,"rank":61},{"keyword":"weight loss","numberOfApps":6774,"searchVolume":47.0,"chance":48,"rank":5},{"keyword":"weight loss fitness by verv","numberOfApps":42,"searchVolume":5.0,"chance":46,"rank":8},{"keyword":"weight loss tracker","numberOfApps":1612,"searchVolume":50.0,"chance":60,"rank":11},{"keyword":"weight management","numberOfApps":1730,"searchVolume":5.0,"chance":74,"rank":155},{"keyword":"weight monitor","numberOfApps":11074,"searchVolume":5.0,"chance":80,"rank":174},{"keyword":"weight tracker","numberOfApps":1726,"searchVolume":43.0,"chance":57,"rank":11},{"keyword":"weight tracker free","numberOfApps":932,"searchVolume":5.0,"chance":54,"rank":3},{"keyword":"weight tracking","numberOfApps":1995,"searchVolume":5.0,"chance":58,"rank":74},{"keyword":"weight tracking app","numberOfApps":1995,"searchVolume":5.0,"chance":44,"rank":11},{"keyword":"weight tracking apps","numberOfApps":1995,"searchVolume":5.0,"chance":46,"rank":15},{"keyword":"weight training","numberOfApps":2881,"searchVolume":24.0,"chance":54,"rank":9},{"keyword":"weight training women","numberOfApps":2293,"searchVolume":5.0,"chance":65,"rank":22},{"keyword":"weight training workouts","numberOfApps":2666,"searchVolume":21.0,"chance":61,"rank":8},{"keyword":"weight watcher","numberOfApps":1700,"searchVolume":5.0,"chance":71,"rank":232},{"keyword":"weightloss tracker","numberOfApps":1612,"searchVolume":21.0,"chance":50,"rank":9},{"keyword":"weights","numberOfApps":11423,"searchVolume":16.0,"chance":72,"rank":34},{"keyword":"wight","numberOfApps":11151,"searchVolume":5.0,"chance":52,"rank":130},{"keyword":"womens fitness","numberOfApps":155600,"searchVolume":10.0,"chance":93,"rank":102},{"keyword":"work","numberOfApps":25581,"searchVolume":34.0,"chance":48,"rank":27},{"keyword":"work out","numberOfApps":12604,"searchVolume":39.0,"chance":50,"rank":2},{"keyword":"work out app","numberOfApps":12595,"searchVolume":23.0,"chance":48,"rank":5},{"keyword":"work out apps","numberOfApps":12596,"searchVolume":15.0,"chance":47,"rank":4},{"keyword":"work out apps free","numberOfApps":6315,"searchVolume":5.0,"chance":50,"rank":6},{"keyword":"work put","numberOfApps":12517,"searchVolume":5.0,"chance":69,"rank":3},{"keyword":"work-out","numberOfApps":12556,"searchVolume":39.0,"chance":57,"rank":3},{"keyword":"workout","numberOfApps":156524,"searchVolume":58.0,"chance":48,"rank":3},{"keyword":"workout \u0026 fitness exercises","numberOfApps":10516,"searchVolume":16.0,"chance":53,"rank":1},{"keyword":"workout app","numberOfApps":156514,"searchVolume":38.0,"chance":43,"rank":4},{"keyword":"workout apps","numberOfApps":156524,"searchVolume":28.0,"chance":42,"rank":3},{"keyword":"workout apps for free","numberOfApps":90348,"searchVolume":5.0,"chance":38,"rank":9},{"keyword":"workout buddy","numberOfApps":12536,"searchVolume":5.0,"chance":66,"rank":113},{"keyword":"workout calendar","numberOfApps":994,"searchVolume":5.0,"chance":48,"rank":4},{"keyword":"workout challenge","numberOfApps":5388,"searchVolume":5.0,"chance":71,"rank":17},{"keyword":"workout challenges","numberOfApps":1788,"searchVolume":5.0,"chance":76,"rank":34},{"keyword":"workout diary","numberOfApps":2163,"searchVolume":5.0,"chance":56,"rank":17},{"keyword":"workout exercises","numberOfApps":10798,"searchVolume":5.0,"chance":72,"rank":104},{"keyword":"workout for kids","numberOfApps":14246,"searchVolume":18.0,"chance":45,"rank":6},{"keyword":"workout for women","numberOfApps":13513,"searchVolume":41.0,"chance":52,"rank":16},{"keyword":"workout free","numberOfApps":90348,"searchVolume":23.0,"chance":41,"rank":24},{"keyword":"workout games","numberOfApps":15431,"searchVolume":19.0,"chance":43,"rank":19},{"keyword":"workout gear","numberOfApps":90428,"searchVolume":5.0,"chance":30,"rank":42},{"keyword":"workout plan","numberOfApps":6160,"searchVolume":21.0,"chance":48,"rank":5},{"keyword":"workout planner","numberOfApps":5049,"searchVolume":38.0,"chance":56,"rank":6},{"keyword":"workout planning","numberOfApps":959,"searchVolume":5.0,"chance":49,"rank":17},{"keyword":"workout routine","numberOfApps":1425,"searchVolume":5.0,"chance":70,"rank":87},{"keyword":"workout routines","numberOfApps":12739,"searchVolume":5.0,"chance":67,"rank":246},{"keyword":"workout schedule","numberOfApps":1714,"searchVolume":5.0,"chance":85,"rank":67},{"keyword":"workout timer","numberOfApps":6808,"searchVolume":33.0,"chance":62,"rank":9},{"keyword":"workout tracker","numberOfApps":11526,"searchVolume":30.0,"chance":46,"rank":9},{"keyword":"workouts","numberOfApps":13988,"searchVolume":33.0,"chance":53,"rank":3},{"keyword":"workouts free","numberOfApps":7287,"searchVolume":5.0,"chance":48,"rank":12},{"keyword":"wright","numberOfApps":11861,"searchVolume":5.0,"chance":50,"rank":129},{"keyword":"xercise4less","numberOfApps":39,"searchVolume":35.0,"chance":51,"rank":4},{"keyword":"yearly planner","numberOfApps":7251,"searchVolume":5.0,"chance":64,"rank":135}],"success":true,"status":"success"}