{"data":[{"keyword":"#жкх","numberOfApps":326,"searchVolume":41.0,"chance":47,"rank":11},{"keyword":"aapl","numberOfApps":5410,"searchVolume":32.0,"chance":63,"rank":27},{"keyword":"abd","numberOfApps":34437,"searchVolume":25.0,"chance":33,"rank":110},{"keyword":"all apps","numberOfApps":78424,"searchVolume":19.0,"chance":0,"rank":207},{"keyword":"analyse","numberOfApps":2875,"searchVolume":23.0,"chance":42,"rank":1},{"keyword":"and","numberOfApps":34001,"searchVolume":35.0,"chance":33,"rank":113},{"keyword":"aplle watch","numberOfApps":28075,"searchVolume":51.0,"chance":45,"rank":40},{"keyword":"app","numberOfApps":78380,"searchVolume":39.0,"chance":0,"rank":209},{"keyword":"app store free","numberOfApps":996963,"searchVolume":21.0,"chance":23,"rank":182},{"keyword":"appel watch","numberOfApps":20149,"searchVolume":51.0,"chance":38,"rank":33},{"keyword":"apple","numberOfApps":5657,"searchVolume":53.0,"chance":86,"rank":83},{"keyword":"apple pay","numberOfApps":9632,"searchVolume":41.0,"chance":33,"rank":4},{"keyword":"apple pay приложение","numberOfApps":9608,"searchVolume":13.0,"chance":29,"rank":3},{"keyword":"apple watch","numberOfApps":20185,"searchVolume":51.0,"chance":67,"rank":51},{"keyword":"apple watch игры","numberOfApps":20081,"searchVolume":15.0,"chance":48,"rank":31},{"keyword":"applepay","numberOfApps":33610,"searchVolume":41.0,"chance":37,"rank":3},{"keyword":"apps","numberOfApps":78380,"searchVolume":39.0,"chance":0,"rank":209},{"keyword":"apps on sale","numberOfApps":78424,"searchVolume":21.0,"chance":0,"rank":207},{"keyword":"artmoney","numberOfApps":17406,"searchVolume":41.0,"chance":45,"rank":8},{"keyword":"best free apps","numberOfApps":59535,"searchVolume":15.0,"chance":35,"rank":231},{"keyword":"big money","numberOfApps":17407,"searchVolume":32.0,"chance":52,"rank":8},{"keyword":"budget","numberOfApps":3776,"searchVolume":33.0,"chance":53,"rank":9},{"keyword":"business","numberOfApps":369884,"searchVolume":41.0,"chance":53,"rank":29},{"keyword":"business app","numberOfApps":369775,"searchVolume":19.0,"chance":36,"rank":22},{"keyword":"businessman","numberOfApps":369560,"searchVolume":31.0,"chance":47,"rank":20},{"keyword":"card","numberOfApps":53338,"searchVolume":33.0,"chance":46,"rank":3},{"keyword":"cards","numberOfApps":15970,"searchVolume":33.0,"chance":39,"rank":4},{"keyword":"download apps","numberOfApps":78424,"searchVolume":31.0,"chance":28,"rank":207},{"keyword":"finance","numberOfApps":92455,"searchVolume":35.0,"chance":60,"rank":14},{"keyword":"finances","numberOfApps":92344,"searchVolume":35.0,"chance":37,"rank":15},{"keyword":"financial","numberOfApps":94298,"searchVolume":35.0,"chance":47,"rank":18},{"keyword":"fre","numberOfApps":1000784,"searchVolume":32.0,"chance":27,"rank":171},{"keyword":"free","numberOfApps":996880,"searchVolume":41.0,"chance":18,"rank":200},{"keyword":"free ...","numberOfApps":997007,"searchVolume":41.0,"chance":23,"rank":233},{"keyword":"free app","numberOfApps":59517,"searchVolume":32.0,"chance":2,"rank":209},{"keyword":"free apps","numberOfApps":59517,"searchVolume":32.0,"chance":2,"rank":209},{"keyword":"free cash","numberOfApps":14771,"searchVolume":21.0,"chance":56,"rank":18},{"keyword":"free messages","numberOfApps":55379,"searchVolume":21.0,"chance":15,"rank":60},{"keyword":"fund","numberOfApps":2025,"searchVolume":31.0,"chance":69,"rank":2},{"keyword":"funds","numberOfApps":2066,"searchVolume":31.0,"chance":75,"rank":2},{"keyword":"gogle карты","numberOfApps":4524,"searchVolume":46.0,"chance":32,"rank":20},{"keyword":"google карты","numberOfApps":5088,"searchVolume":46.0,"chance":28,"rank":12},{"keyword":"hot app","numberOfApps":78424,"searchVolume":23.0,"chance":20,"rank":207},{"keyword":"ipad app","numberOfApps":140231,"searchVolume":17.0,"chance":11,"rank":186},{"keyword":"iwatch","numberOfApps":19857,"searchVolume":35.0,"chance":39,"rank":32},{"keyword":"kivi кошелек","numberOfApps":61,"searchVolume":52.0,"chance":33,"rank":4},{"keyword":"kiwi кошелек","numberOfApps":721,"searchVolume":31.0,"chance":36,"rank":4},{"keyword":"livewatch","numberOfApps":20644,"searchVolume":12.0,"chance":19,"rank":27},{"keyword":"llc","numberOfApps":138540,"searchVolume":33.0,"chance":20,"rank":30},{"keyword":"many","numberOfApps":18347,"searchVolume":31.0,"chance":48,"rank":12},{"keyword":"messages","numberOfApps":61046,"searchVolume":35.0,"chance":21,"rank":47},{"keyword":"mobile app","numberOfApps":78380,"searchVolume":31.0,"chance":4,"rank":209},{"keyword":"mobile apps","numberOfApps":78380,"searchVolume":31.0,"chance":4,"rank":209},{"keyword":"mon","numberOfApps":23017,"searchVolume":31.0,"chance":53,"rank":12},{"keyword":"monefy","numberOfApps":17410,"searchVolume":31.0,"chance":52,"rank":21},{"keyword":"monetary","numberOfApps":17443,"searchVolume":21.0,"chance":45,"rank":11},{"keyword":"money","numberOfApps":17492,"searchVolume":41.0,"chance":50,"rank":13},{"keyword":"money app","numberOfApps":19470,"searchVolume":24.0,"chance":47,"rank":10},{"keyword":"money maker","numberOfApps":9458,"searchVolume":28.0,"chance":59,"rank":18},{"keyword":"moneyflow","numberOfApps":17415,"searchVolume":24.0,"chance":56,"rank":20},{"keyword":"moneyfy","numberOfApps":17399,"searchVolume":31.0,"chance":52,"rank":20},{"keyword":"nice apps","numberOfApps":78424,"searchVolume":13.0,"chance":33,"rank":207},{"keyword":"payment","numberOfApps":5788,"searchVolume":32.0,"chance":49,"rank":2},{"keyword":"payments","numberOfApps":5790,"searchVolume":32.0,"chance":52,"rank":2},{"keyword":"paypal","numberOfApps":679,"searchVolume":52.0,"chance":48,"rank":9},{"keyword":"phone app","numberOfApps":78380,"searchVolume":22.0,"chance":4,"rank":209},{"keyword":"qivi","numberOfApps":72,"searchVolume":54.0,"chance":42,"rank":7},{"keyword":"qiwi","numberOfApps":760,"searchVolume":54.0,"chance":39,"rank":8},{"keyword":"qiwi wallet","numberOfApps":71,"searchVolume":34.0,"chance":39,"rank":6},{"keyword":"qiwi кошелек","numberOfApps":39,"searchVolume":44.0,"chance":35,"rank":5},{"keyword":"sberbank online","numberOfApps":52,"searchVolume":51.0,"chance":33,"rank":8},{"keyword":"search apps","numberOfApps":78424,"searchVolume":15.0,"chance":27,"rank":207},{"keyword":"snd","numberOfApps":34171,"searchVolume":23.0,"chance":44,"rank":112},{"keyword":"tap app","numberOfApps":78427,"searchVolume":12.0,"chance":0,"rank":207},{"keyword":"tinkoff","numberOfApps":43,"searchVolume":49.0,"chance":36,"rank":7},{"keyword":"top app","numberOfApps":78424,"searchVolume":19.0,"chance":19,"rank":207},{"keyword":"top apps","numberOfApps":78424,"searchVolume":19.0,"chance":25,"rank":207},{"keyword":"transfer","numberOfApps":4713,"searchVolume":32.0,"chance":55,"rank":10},{"keyword":"transfers","numberOfApps":4691,"searchVolume":24.0,"chance":55,"rank":9},{"keyword":"visa qiwi wallet","numberOfApps":81,"searchVolume":33.0,"chance":41,"rank":6},{"keyword":"visa wallet","numberOfApps":5605,"searchVolume":15.0,"chance":51,"rank":6},{"keyword":"wallet","numberOfApps":4874,"searchVolume":41.0,"chance":47,"rank":4},{"keyword":"wallet apple pay","numberOfApps":14326,"searchVolume":17.0,"chance":47,"rank":2},{"keyword":"wallets","numberOfApps":4626,"searchVolume":41.0,"chance":43,"rank":7},{"keyword":"watch","numberOfApps":28866,"searchVolume":41.0,"chance":23,"rank":50},{"keyword":"watch app","numberOfApps":28817,"searchVolume":25.0,"chance":35,"rank":50},{"keyword":"y","numberOfApps":553,"searchVolume":49.0,"chance":14,"rank":14},{"keyword":"yadex","numberOfApps":348,"searchVolume":63.0,"chance":21,"rank":6},{"keyword":"yan","numberOfApps":9740,"searchVolume":41.0,"chance":20,"rank":9},{"keyword":"yandere","numberOfApps":436,"searchVolume":33.0,"chance":39,"rank":10},{"keyword":"yandex","numberOfApps":368,"searchVolume":63.0,"chance":21,"rank":13},{"keyword":"yandex avia","numberOfApps":362,"searchVolume":34.0,"chance":36,"rank":23},{"keyword":"yandex карта","numberOfApps":372,"searchVolume":46.0,"chance":19,"rank":11},{"keyword":"yandex карты","numberOfApps":76,"searchVolume":46.0,"chance":26,"rank":6},{"keyword":"yandex транспорт","numberOfApps":362,"searchVolume":31.0,"chance":20,"rank":18},{"keyword":"yandexmail","numberOfApps":348,"searchVolume":43.0,"chance":22,"rank":24},{"keyword":"yandexmoney","numberOfApps":20,"searchVolume":41.0,"chance":34,"rank":1},{"keyword":"youwatch","numberOfApps":28035,"searchVolume":17.0,"chance":19,"rank":27},{"keyword":"азарт","numberOfApps":4627,"searchVolume":33.0,"chance":33,"rank":14},{"keyword":"арты","numberOfApps":5054,"searchVolume":46.0,"chance":35,"rank":13},{"keyword":"банк онлайн","numberOfApps":298,"searchVolume":41.0,"chance":26,"rank":7},{"keyword":"банковские карты","numberOfApps":4511,"searchVolume":38.0,"chance":47,"rank":12},{"keyword":"безплатно","numberOfApps":121276,"searchVolume":31.0,"chance":26,"rank":190},{"keyword":"бесплатная","numberOfApps":122045,"searchVolume":49.0,"chance":51,"rank":232},{"keyword":"бесплатно","numberOfApps":121257,"searchVolume":49.0,"chance":22,"rank":210},{"keyword":"бизнес","numberOfApps":12280,"searchVolume":44.0,"chance":51,"rank":31},{"keyword":"бизнес игра","numberOfApps":12265,"searchVolume":41.0,"chance":56,"rank":45},{"keyword":"бизнес игры","numberOfApps":12268,"searchVolume":41.0,"chance":57,"rank":38},{"keyword":"бизнес новости","numberOfApps":15520,"searchVolume":28.0,"chance":45,"rank":52},{"keyword":"бизнес приложение","numberOfApps":12269,"searchVolume":21.0,"chance":39,"rank":38},{"keyword":"бизнес симулятор","numberOfApps":17434,"searchVolume":27.0,"chance":50,"rank":40},{"keyword":"бизнес фм","numberOfApps":12268,"searchVolume":41.0,"chance":43,"rank":31},{"keyword":"бизнес-приложение","numberOfApps":12270,"searchVolume":21.0,"chance":39,"rank":38},{"keyword":"бизнеса","numberOfApps":12296,"searchVolume":44.0,"chance":43,"rank":34},{"keyword":"бизнесмен","numberOfApps":12281,"searchVolume":39.0,"chance":50,"rank":38},{"keyword":"бюджет","numberOfApps":538,"searchVolume":41.0,"chance":52,"rank":18},{"keyword":"бюджетные","numberOfApps":526,"searchVolume":41.0,"chance":54,"rank":7},{"keyword":"вебмани","numberOfApps":3,"searchVolume":44.0,"chance":100,"rank":2},{"keyword":"гугл карты","numberOfApps":4521,"searchVolume":58.0,"chance":28,"rank":17},{"keyword":"гуглкарты","numberOfApps":4523,"searchVolume":58.0,"chance":26,"rank":19},{"keyword":"денди","numberOfApps":11727,"searchVolume":42.0,"chance":53,"rank":9},{"keyword":"денег","numberOfApps":1857,"searchVolume":32.0,"chance":46,"rank":7},{"keyword":"денежные переводы","numberOfApps":180,"searchVolume":35.0,"chance":40,"rank":3},{"keyword":"деньги","numberOfApps":1787,"searchVolume":51.0,"chance":46,"rank":1},{"keyword":"деньги бесплатно","numberOfApps":973,"searchVolume":27.0,"chance":49,"rank":5},{"keyword":"деньги за лайки","numberOfApps":1775,"searchVolume":31.0,"chance":46,"rank":6},{"keyword":"деньги игра","numberOfApps":1775,"searchVolume":31.0,"chance":56,"rank":8},{"keyword":"деньги игры","numberOfApps":1775,"searchVolume":31.0,"chance":60,"rank":6},{"keyword":"деньги на счет","numberOfApps":1774,"searchVolume":21.0,"chance":48,"rank":6},{"keyword":"деньги на телефон","numberOfApps":1774,"searchVolume":31.0,"chance":45,"rank":5},{"keyword":"деньги ок","numberOfApps":1781,"searchVolume":23.0,"chance":48,"rank":31},{"keyword":"дисконтные карты","numberOfApps":4508,"searchVolume":36.0,"chance":42,"rank":4},{"keyword":"дневник расходов","numberOfApps":528,"searchVolume":21.0,"chance":52,"rank":23},{"keyword":"домашние деньги","numberOfApps":1774,"searchVolume":38.0,"chance":50,"rank":3},{"keyword":"домашние финансы","numberOfApps":4502,"searchVolume":22.0,"chance":60,"rank":30},{"keyword":"домашний бюджет","numberOfApps":525,"searchVolume":23.0,"chance":56,"rank":16},{"keyword":"жкх","numberOfApps":326,"searchVolume":41.0,"chance":47,"rank":12},{"keyword":"журнал расходов","numberOfApps":232,"searchVolume":32.0,"chance":54,"rank":36},{"keyword":"зарабатывай деньги","numberOfApps":1774,"searchVolume":41.0,"chance":47,"rank":4},{"keyword":"заработай деньги","numberOfApps":1774,"searchVolume":41.0,"chance":51,"rank":4},{"keyword":"заработать деньги","numberOfApps":130,"searchVolume":41.0,"chance":44,"rank":6},{"keyword":"игра карты","numberOfApps":4583,"searchVolume":38.0,"chance":47,"rank":30},{"keyword":"игры на деньги","numberOfApps":1774,"searchVolume":36.0,"chance":52,"rank":15},{"keyword":"индекс","numberOfApps":984,"searchVolume":46.0,"chance":22,"rank":37},{"keyword":"йандекс","numberOfApps":862,"searchVolume":73.0,"chance":19,"rank":35},{"keyword":"как заработать деньги","numberOfApps":1775,"searchVolume":46.0,"chance":49,"rank":16},{"keyword":"калькулятор расходов","numberOfApps":1947,"searchVolume":22.0,"chance":48,"rank":17},{"keyword":"карт","numberOfApps":13568,"searchVolume":61.0,"chance":21,"rank":9},{"keyword":"карти","numberOfApps":6801,"searchVolume":32.0,"chance":40,"rank":21},{"keyword":"карто","numberOfApps":4515,"searchVolume":61.0,"chance":26,"rank":6},{"keyword":"карточки скидочные","numberOfApps":57,"searchVolume":25.0,"chance":28,"rank":4},{"keyword":"карточные","numberOfApps":6514,"searchVolume":31.0,"chance":56,"rank":40},{"keyword":"карты","numberOfApps":4513,"searchVolume":61.0,"chance":37,"rank":11},{"keyword":"карты gps","numberOfApps":4508,"searchVolume":27.0,"chance":41,"rank":11},{"keyword":"карты без интернета","numberOfApps":4509,"searchVolume":31.0,"chance":28,"rank":9},{"keyword":"карты играть","numberOfApps":4509,"searchVolume":31.0,"chance":42,"rank":21},{"keyword":"карты магазинов","numberOfApps":4520,"searchVolume":31.0,"chance":31,"rank":6},{"keyword":"карты москвы","numberOfApps":4541,"searchVolume":51.0,"chance":30,"rank":16},{"keyword":"карты оффлайн","numberOfApps":4509,"searchVolume":32.0,"chance":38,"rank":16},{"keyword":"карты паук","numberOfApps":4955,"searchVolume":32.0,"chance":52,"rank":26},{"keyword":"карты россии","numberOfApps":189,"searchVolume":52.0,"chance":38,"rank":7},{"keyword":"карты скидок","numberOfApps":86,"searchVolume":31.0,"chance":40,"rank":12},{"keyword":"карты спб","numberOfApps":4509,"searchVolume":49.0,"chance":28,"rank":7},{"keyword":"кашелек","numberOfApps":391,"searchVolume":41.0,"chance":33,"rank":2},{"keyword":"киви","numberOfApps":95,"searchVolume":56.0,"chance":38,"rank":8},{"keyword":"киви валет","numberOfApps":91,"searchVolume":33.0,"chance":38,"rank":7},{"keyword":"киви карта","numberOfApps":91,"searchVolume":32.0,"chance":38,"rank":7},{"keyword":"киви кашелек","numberOfApps":93,"searchVolume":41.0,"chance":39,"rank":9},{"keyword":"киви кошелек","numberOfApps":97,"searchVolume":52.0,"chance":42,"rank":8},{"keyword":"киви кошелёк","numberOfApps":93,"searchVolume":52.0,"chance":39,"rank":9},{"keyword":"кидать деньги","numberOfApps":1775,"searchVolume":31.0,"chance":45,"rank":3},{"keyword":"контроль расходов","numberOfApps":194,"searchVolume":31.0,"chance":53,"rank":20},{"keyword":"корт","numberOfApps":4535,"searchVolume":33.0,"chance":27,"rank":7},{"keyword":"кошелек","numberOfApps":452,"searchVolume":46.0,"chance":32,"rank":6},{"keyword":"кошелёк","numberOfApps":410,"searchVolume":42.0,"chance":27,"rank":2},{"keyword":"край инвест банк","numberOfApps":1256,"searchVolume":41.0,"chance":40,"rank":3},{"keyword":"крайинвест банк","numberOfApps":1256,"searchVolume":41.0,"chance":40,"rank":3},{"keyword":"купюры","numberOfApps":34,"searchVolume":33.0,"chance":55,"rank":14},{"keyword":"купюры 2000","numberOfApps":23,"searchVolume":31.0,"chance":50,"rank":9},{"keyword":"купюры 2017","numberOfApps":26,"searchVolume":25.0,"chance":51,"rank":9},{"keyword":"купюры 2018","numberOfApps":24,"searchVolume":31.0,"chance":52,"rank":10},{"keyword":"купюры 3d","numberOfApps":21,"searchVolume":17.0,"chance":50,"rank":9},{"keyword":"легкие деньги","numberOfApps":1775,"searchVolume":36.0,"chance":50,"rank":11},{"keyword":"леньги","numberOfApps":1775,"searchVolume":51.0,"chance":44,"rank":2},{"keyword":"личные финансы","numberOfApps":4542,"searchVolume":27.0,"chance":55,"rank":28},{"keyword":"личный бюджет","numberOfApps":552,"searchVolume":23.0,"chance":53,"rank":17},{"keyword":"менеджер расходов","numberOfApps":176,"searchVolume":21.0,"chance":53,"rank":55},{"keyword":"метро москвы","numberOfApps":192,"searchVolume":53.0,"chance":38,"rank":11},{"keyword":"мобильный кошелек","numberOfApps":390,"searchVolume":28.0,"chance":24,"rank":3},{"keyword":"мои карты","numberOfApps":110,"searchVolume":32.0,"chance":34,"rank":8},{"keyword":"мой бюджет","numberOfApps":537,"searchVolume":22.0,"chance":51,"rank":15},{"keyword":"московский метрополитен","numberOfApps":113,"searchVolume":41.0,"chance":31,"rank":8},{"keyword":"московское метро","numberOfApps":2209,"searchVolume":43.0,"chance":32,"rank":9},{"keyword":"на карту","numberOfApps":95,"searchVolume":35.0,"chance":55,"rank":5},{"keyword":"нужные приложения","numberOfApps":121406,"searchVolume":28.0,"chance":20,"rank":194},{"keyword":"онлайн банк","numberOfApps":423,"searchVolume":41.0,"chance":26,"rank":9},{"keyword":"оплата","numberOfApps":422,"searchVolume":39.0,"chance":38,"rank":1},{"keyword":"оплата жкх","numberOfApps":355,"searchVolume":34.0,"chance":46,"rank":8},{"keyword":"оплата игр","numberOfApps":421,"searchVolume":14.0,"chance":30,"rank":12},{"keyword":"оплата интернета","numberOfApps":421,"searchVolume":31.0,"chance":32,"rank":4},{"keyword":"оплата картой","numberOfApps":421,"searchVolume":31.0,"chance":30,"rank":2},{"keyword":"оплата карты","numberOfApps":18,"searchVolume":31.0,"chance":54,"rank":1},{"keyword":"оплата кредита","numberOfApps":421,"searchVolume":28.0,"chance":37,"rank":3},{"keyword":"оплата кредитов","numberOfApps":421,"searchVolume":28.0,"chance":30,"rank":3},{"keyword":"оплата налогов","numberOfApps":125,"searchVolume":32.0,"chance":49,"rank":10},{"keyword":"оплата телефона","numberOfApps":421,"searchVolume":41.0,"chance":31,"rank":2},{"keyword":"оплата телефоном","numberOfApps":421,"searchVolume":41.0,"chance":43,"rank":4},{"keyword":"оплата услуг","numberOfApps":421,"searchVolume":25.0,"chance":50,"rank":14},{"keyword":"переводы","numberOfApps":2376,"searchVolume":61.0,"chance":51,"rank":7},{"keyword":"платежи","numberOfApps":217,"searchVolume":32.0,"chance":42,"rank":3},{"keyword":"подлинность купюры","numberOfApps":20,"searchVolume":22.0,"chance":50,"rank":9},{"keyword":"подсчет расходов","numberOfApps":168,"searchVolume":21.0,"chance":50,"rank":30},{"keyword":"полезные приложения","numberOfApps":121406,"searchVolume":36.0,"chance":51,"rank":201},{"keyword":"построить бизнес","numberOfApps":12269,"searchVolume":12.0,"chance":41,"rank":29},{"keyword":"приложение вконтакте","numberOfApps":121696,"searchVolume":36.0,"chance":39,"rank":228},{"keyword":"приложение дня бесплатно","numberOfApps":122369,"searchVolume":14.0,"chance":56,"rank":220},{"keyword":"приложение одноклассники","numberOfApps":121369,"searchVolume":33.0,"chance":37,"rank":205},{"keyword":"приложение ферби","numberOfApps":121257,"searchVolume":25.0,"chance":69,"rank":204},{"keyword":"приложения apple","numberOfApps":127567,"searchVolume":21.0,"chance":42,"rank":163},{"keyword":"приложения для вк","numberOfApps":121769,"searchVolume":31.0,"chance":46,"rank":224},{"keyword":"приложения для музыки","numberOfApps":121271,"searchVolume":39.0,"chance":19,"rank":188},{"keyword":"приложения дня","numberOfApps":122000,"searchVolume":21.0,"chance":47,"rank":219},{"keyword":"приложения на айфон","numberOfApps":121772,"searchVolume":32.0,"chance":34,"rank":227},{"keyword":"проверить 2000","numberOfApps":23,"searchVolume":21.0,"chance":51,"rank":9},{"keyword":"проверить купюры","numberOfApps":22,"searchVolume":22.0,"chance":52,"rank":10},{"keyword":"расходов","numberOfApps":491,"searchVolume":35.0,"chance":53,"rank":32},{"keyword":"рты","numberOfApps":4514,"searchVolume":23.0,"chance":32,"rank":7},{"keyword":"с карты на карту","numberOfApps":49,"searchVolume":33.0,"chance":59,"rank":10},{"keyword":"сбербанк","numberOfApps":255,"searchVolume":61.0,"chance":44,"rank":22},{"keyword":"сбербанк онлайн","numberOfApps":89,"searchVolume":66.0,"chance":33,"rank":10},{"keyword":"свой бизнес","numberOfApps":12290,"searchVolume":31.0,"chance":45,"rank":22},{"keyword":"семейный бюджет","numberOfApps":527,"searchVolume":34.0,"chance":54,"rank":13},{"keyword":"скачать карты","numberOfApps":4511,"searchVolume":36.0,"chance":32,"rank":6},{"keyword":"скачать киви кошелек","numberOfApps":39,"searchVolume":35.0,"chance":33,"rank":4},{"keyword":"скидочные карты","numberOfApps":4513,"searchVolume":39.0,"chance":42,"rank":2},{"keyword":"тиньков","numberOfApps":39,"searchVolume":42.0,"chance":34,"rank":6},{"keyword":"тинькоф","numberOfApps":41,"searchVolume":55.0,"chance":35,"rank":7},{"keyword":"тинькофф","numberOfApps":37,"searchVolume":55.0,"chance":35,"rank":6},{"keyword":"умный бюджет","numberOfApps":541,"searchVolume":17.0,"chance":61,"rank":17},{"keyword":"учет","numberOfApps":563,"searchVolume":31.0,"chance":52,"rank":29},{"keyword":"учет времени","numberOfApps":214,"searchVolume":22.0,"chance":59,"rank":22},{"keyword":"учет денег","numberOfApps":187,"searchVolume":21.0,"chance":51,"rank":33},{"keyword":"учет долгов","numberOfApps":175,"searchVolume":21.0,"chance":55,"rank":21},{"keyword":"учет доходов и расходов","numberOfApps":160,"searchVolume":23.0,"chance":51,"rank":32},{"keyword":"учет затрат","numberOfApps":562,"searchVolume":21.0,"chance":54,"rank":34},{"keyword":"учет расходов","numberOfApps":160,"searchVolume":31.0,"chance":50,"rank":59},{"keyword":"учет расходов и доходов","numberOfApps":160,"searchVolume":32.0,"chance":51,"rank":48},{"keyword":"учет финансов","numberOfApps":251,"searchVolume":27.0,"chance":52,"rank":26},{"keyword":"учёт расходов","numberOfApps":164,"searchVolume":32.0,"chance":51,"rank":17},{"keyword":"финам","numberOfApps":4491,"searchVolume":49.0,"chance":52,"rank":21},{"keyword":"финанс","numberOfApps":4492,"searchVolume":41.0,"chance":49,"rank":14},{"keyword":"финансист","numberOfApps":4529,"searchVolume":35.0,"chance":51,"rank":14},{"keyword":"финансовый","numberOfApps":4527,"searchVolume":31.0,"chance":42,"rank":19},{"keyword":"финансы","numberOfApps":4499,"searchVolume":41.0,"chance":52,"rank":12},{"keyword":"экономить деньги","numberOfApps":1775,"searchVolume":23.0,"chance":56,"rank":4},{"keyword":"я","numberOfApps":231,"searchVolume":54.0,"chance":17,"rank":13},{"keyword":"яндекс","numberOfApps":861,"searchVolume":73.0,"chance":23,"rank":21},{"keyword":"яндекс авиа","numberOfApps":971,"searchVolume":49.0,"chance":21,"rank":19},{"keyword":"яндекс деньги","numberOfApps":53,"searchVolume":52.0,"chance":38,"rank":1},{"keyword":"яндекс карта","numberOfApps":10451,"searchVolume":61.0,"chance":23,"rank":4},{"keyword":"яндекс карты","numberOfApps":125,"searchVolume":61.0,"chance":25,"rank":6},{"keyword":"яндекс карты офлайн","numberOfApps":966,"searchVolume":21.0,"chance":22,"rank":6},{"keyword":"яндекс кошелек","numberOfApps":859,"searchVolume":46.0,"chance":25,"rank":1},{"keyword":"яндекс поезда","numberOfApps":844,"searchVolume":32.0,"chance":22,"rank":35},{"keyword":"яндекс путешествия","numberOfApps":17831,"searchVolume":33.0,"chance":32,"rank":23},{"keyword":"яндекс.диск","numberOfApps":853,"searchVolume":53.0,"chance":23,"rank":14},{"keyword":"яндекс.музыка","numberOfApps":858,"searchVolume":61.0,"chance":21,"rank":35}],"success":true,"status":"success"}